{"min_level": {"effects_raw": [[1, 1, 70, [0, 0, 290, 50]]], "cost": 16, "effects": ["Magic damage (5.8x, MAG) to one enemy (ignore cover and reflect)"]}, "name": "Photon Stream", "max_level": {"effects_raw": [[1, 1, 70, [0, 0, 410, 50]]], "cost": 16, "effects": ["Magic damage (8.2x, MAG) to one enemy (ignore cover and reflect)"]}, "move_type": 1, "attack_count": [10], "levels": 25, "element_inflict": null, "cost": 0, "attack_frames": [[106, 115, 124, 133, 143, 152, 161, 170, 178, 191]], "effect_frames": [[0, 0, 189]], "strings": {"name": ["Photon Stream", "\u9b54\u5c0e\u5149\u5b50\u70ae", "\ub9c8\ub3c4 \uad11\uc790\ud3ec", "Rayon de photons", "Photonenstrom", "Rayo de fotones"], "desc": ["Partial unmitigated magic damage to one enemy", "\u5c0d1\u540d\u6575\u4eba\u767c\u52d5\u7121\u8996\u9b54\u6cd5\u9632\u79a6\u7684\u653b\u64ca", "\uc801 1\uba85\uc5d0\uac8c \uc77c\ubd80 \ub9c8\ubc95\ubc29\uc5b4 \ubb34\uc2dc \ud53c\ud574", "Inflige des d\u00e9g\u00e2ts magiques en partie fixes \u00e0 un ennemi", "Teilweise direkter Magieschaden, ein Ziel", "Da\u00f1o m\u00e1gico absoluto parcial al enemigo"]}, "damage_type": "Magic"}