{"slot": "Weapon", "compendium_shown": true, "price_buy": 1000000, "requirements": null, "name": "Necro Dagger", "type_id": 1, "skills": [910444], "is_twohanded": false, "rarity": 7, "compendium_id": 90106, "dmg_variance": null, "slot_id": 1, "effects": ["Grants 'Zombie Flames' ability."], "price_sell": 1000, "stats": {"status_inflict": null, "status_resist": null, "element_resist": null, "HP": 0, "ATK": 78, "element_inflict": ["Fire", "Dark"], "MP": 0, "MAG": 30, "SPR": 0, "DEF": 0}, "icon": "global_equip_10042.png", "type": "Dagger", "strings": {"name": ["Necro Dagger", "\u6b7b\u5c4d\u77ed\u528d", "\uac15\ub839\uc220 \ub2e8\uac80", "N\u00e9crodague", "Necrodolch", "Necrodaga"], "desc_short": ["This dagger\u2019s origin is unknown, but it appears to be for ceremonial use.", "\u7528\u65bc\u67d0\u7a2e\u5100\u5f0f\u7684\u5315\u9996", "\ucd9c\ucc98\ub294 \ubd88\ubd84\uba85\ud558\ub098, \uc758\uc2dd\uc6a9\uc73c\ub85c \ub9cc\ub4e4\uc5b4\uc9c4 \uac83\uc73c\ub85c \ucd94\uc815\ub418\ub294 \ub2e8\uac80.", "Cette dague \u00e0 l'origine inconnue semble \u00eatre r\u00e9serv\u00e9e \u00e0 un usage c\u00e9r\u00e9monial.", "Ein f\u00fcr den zeremionellen Gebrauch angefertigter Dolch.", "El origen de esta daga es desconocido. Parece que se hizo para usarse en ceremonias."], "desc_long": ["This dagger\u2019s origin is unknown, but it appears to be for ceremonial use. The engravings on its hilt suggest that the rite in which it is used is performed before a live audience, each member of which begging take part.", "\u7528\u65bc\u67d0\u7a2e\u5100\u5f0f\u7684\u5315\u9996\u3002\u63e1\u67c4\u4e0a\u7684\u96d5\u523b\u6697\u793a\u8457\u9019\u500b\u5100\u5f0f\u662f\u5728\u89c0\u773e\u9762\u524d\u57f7\u884c\uff0c\u4e26\u4e14\u89c0\u773e\u5011\u90fd\u5e0c\u671b\u81ea\u5df1\u80fd\u6210\u70ba\u4e0b\u4e00\u500b\u796d\u54c1\u3002", "\ucd9c\ucc98\ub294 \ubd88\ubd84\uba85\ud558\ub098, \uc758\uc2dd\uc6a9\uc73c\ub85c \ub9cc\ub4e4\uc5b4\uc9c4 \uac83\uc73c\ub85c \ucd94\uc815\ub418\ub294 \ub2e8\uac80. \uc790\ub8e8\uc5d0 \uc0c8\uaca8\uc9c4 \ubb38\uad6c\ub294 \ub2e4\uc74c \uc758\uc2dd\uc758 \uc81c\ubb3c\uc774 \ub418\uace0\uc790 \ud558\ub294 \uad00\uac1d \uc55e\uc5d0\uc11c \uc774 \uc758\uc2dd\uc774 \uac70\ud589\ud574\uc84c\uc74c\uc744 \uc554\uc2dc\ud55c\ub2e4.", "Cette dague \u00e0 l'origine inconnue semble \u00eatre r\u00e9serv\u00e9e \u00e0 un usage c\u00e9r\u00e9monial. Les gravures sur sa garde sugg\u00e8rent que le rite pour lequel elle est utilis\u00e9e est effectu\u00e9 devant des spectateurs qui supplient tous d'y participer.", "Ein f\u00fcr den zeremionellen Gebrauch angefertigter Dolch. Die Gravuren an seinem Griff deuten darauf hin, dass die Zeremonien vor einem Publikum durchgef\u00fchrt wurden, aus dem einjeder sich w\u00fcnschte, das n\u00e4chste rituelle Opfer zu sein.", "El origen de esta daga es desconocido. Parece que se hizo para usarse en ceremonias. Los grabados que tiene en su empu\u00f1adura sugieren que el ritual se realiza en frente de una audiencia exaltada que clama por formar parte del mism\u00edsimo ritual."]}, "accuracy": 0}