{"slot": "Weapon", "compendium_shown": true, "price_buy": 400000, "requirements": null, "name": "Shining Splendor", "type_id": 2, "skills": null, "is_twohanded": false, "rarity": 7, "compendium_id": 90006, "dmg_variance": null, "slot_id": 1, "effects": null, "price_sell": 4000, "stats": {"status_inflict": {"Blind": 15}, "status_resist": null, "element_resist": null, "HP": 0, "ATK": 72, "element_inflict": null, "MP": 0, "MAG": 0, "SPR": 0, "DEF": 8}, "icon": "global_item_10034.png", "type": "Sword", "strings": {"name": ["Shining Splendor", "\u5149\u8f1d\u9583\u8000", "\uad11\ud718\uc758 \uac80", "Splendeur \u00e9clatante", "Strahlende Pracht", "Esplendor creciente"], "desc_short": ["A powerful sword forged from various materials under extreme heat.", "\u5c07\u5927\u91cf\u6750\u6599\u7528\u707c\u71b1\u4e4b\u708e\u4e45\u4e45\u7149\u5236\u800c\u6210\u7684\u5f37\u529b\u9577\u528d", "\uc791\uc5f4\ud558\ub294 \ud654\uc5fc \uc18d\uc5d0\uc11c \uc218\ub9ce\uc740 \uc7ac\ub8cc\ub4e4\ub85c \ub9cc\ub4e4\uc5b4\ub0b8 \uae38\uace0\ub3c4 \uac15\ub825\ud55c \uac80.", "\u00c9p\u00e9e forg\u00e9e \u00e0 partir de mat\u00e9riaux chauff\u00e9s \u00e0 une chaleur extr\u00eame.", "Ein m\u00e4chtiges Schwert geschmiedet aus verschiedenen Materialien.", "Una poderosa espada forjada con materiales bajo calor extremo."], "desc_long": ["A blade that is so tedious and expensive to craft, the blacksmith community cringes at the mere mention of this sword. Forging one takes flames so hot they can instantly melt most metals. Few blade-wielders have ever had the privilege of brandishing this blade, the shine of which blinds those who find themselves at the wrong end of one of its attacks.", "\u8a72\u528d\u7684\u88fd\u4f5c\u904e\u7a0b\u975e\u5e38\u7e41\u7463\u4e14\u6210\u672c\u6975\u70ba\u6602\u8cb4\uff0c\u6240\u4ee5\u935b\u51b6\u5e97\u7684\u4eba\u807d\u5230\u8a72\u528d\u7684\u540d\u5b57\u90fd\u6703\u805e\u528d\u55aa\u81bd\u3002\u60f3\u8981\u88fd\u4f5c\u5149\u8f1d\u9583\u8000\u5fc5\u9808\u8981\u6eff\u8db3\u5e7e\u500b\u7279\u6b8a\u689d\u4ef6\u624d\u884c\u3002\u9996\u5148\u662f\u9700\u8981\u80fd\u5920\u7194\u5316\u7d50\u5be6\u91d1\u5c6c\u7684\u696d\u706b\uff0c\u5176\u6b21\u662f\u9700\u8981\u5de5\u5320\u5011\u9577\u6642\u9593\u5fcd\u53d7\u935b\u51b6\u5de5\u5834\u5167\u7684\u9ad8\u6eab\u3002\u4e16\u4e0a\u6709\u8cc7\u683c\u63ee\u821e\u9019\u628a\u540d\u528d\u7684\u528d\u58eb\u528d\u5ba2\u5c48\u6307\u53ef\u6578\u3002\u51e1\u592b\u4fd7\u5b50\u5728\u63ee\u821e\u8a72\u528d\u6642\u90fd\u6703\u88ab\u9583\u8000\u7684\u528d\u5149\u6643\u5f97\u6688\u982d\u8f49\u5411\u3002", "\uc774 \uac80\uc744 \ub9cc\ub4dc\ub294 \ub370\uc5d0\ub294 \uaf64\ub098 \ub9ce\uc740 \ube44\uc6a9\uc774 \ub4dc\ub294 \ub370\ub2e4\uac00 \ubc88\uac70\ub86d\uae30\uae4c\uc9c0 \ud558\uae30 \ub54c\ubb38\uc5d0 \ub300\uc7a5\uac04\uc5d0\uc11c\ub294 \uc774 \uac80\uc758 \uc774\ub984\ub9cc \ub4e4\uc5b4\ub3c4 \uace0\uac1c\ub97c \uc813\ub294\ub2e4. \uad11\ud718\uc758 \uac80\uc740 \ud2b9\uc218\ud55c \uc870\uac74\uc744 \ub9cc\uc871\uc2dc\ud0a4\uc9c0 \uc54a\uc73c\uba74 \ub9cc\ub4e4\uc5b4\ub0bc \uc218 \uc5c6\ub2e4. \ub2e8\ub2e8\ud55c \uae08\uc18d\ub3c4 \ub179\uc5ec\ubc84\ub9b4 \uc815\ub3c4\ub85c \uac15\ud55c \ubd88\uae38\uc774 \ud544\uc694\ud558\ubbc0\ub85c, \uc774 \uac80\uc744 \uc81c\uc791\ud558\ub294 \uc7a5\uc778\ub4e4\uc740 \uc624\ub79c \uc2dc\uac04 \ub3d9\uc548 \ub300\uc7a5\uac04\uc758 \uace0\uc628\uc744 \uacac\ub38c\ub0b4\uc57c\ub9cc \ud55c\ub2e4. \uc18c\uc218\uc758 \uac80\uc0ac\ub9cc\uc774 \uc774 \ubb34\uc2dc\ubb34\uc2dc\ud55c \uac80\uc744 \ud718\ub450\ub97c \uc218 \uc788\ub294 \uc790\uaca9\uc744 \ubd80\uc5ec\ubc1b\ub294\ub370, \uadf8 \ube5b\ub098\ub294 \uce7c\ub0a0\uc744 \ud53c\ud558\uc9c0 \ubabb\ud55c \uc790\ub294 \ub208\uc774 \uba40\uac8c \ub41c\ub2e4.", "Cette lame est si fastidieuse et ch\u00e8re \u00e0 forger que la communaut\u00e9 des forgerons tremble \u00e0 la simple \u00e9vocation de son nom. Les flammes servant \u00e0 forger cette lame sont si chaudes qu'elles peuvent faire fondre la plupart des m\u00e9taux. Bien peu d'\u00e9p\u00e9istes ont eu le privil\u00e8ge de pouvoir brandir cette \u00e9p\u00e9e dont l'\u00e9clat aveugle toutes les personnes se trouvant du mauvais c\u00f4t\u00e9 de la lame.", "Eine Klinge so besonders und teuer, dass jeder Schmied alleine bei seiner Erw\u00e4hnung zusammenzuckt. Ein m\u00e4chtiges Schwert geschmiedet aus verschiedenen Materialien und unter gro\u00dfer Hitze. Um dieses Schwert zu schmieden, braucht es Flammen, die die meisten Metalle zum Schmelzen bringen. Wer dieses Schwert schmiedet, muss die gro\u00dfe Hitze also ertragen k\u00f6nnen. Nur wenige Schwertk\u00e4mpfer durften diese herausragende Klinge schwingen, sein Glanz blendet diejenigen, die sich am anderen Ende der Klinge wiederfinden.", "Una espada que cuesta tanto trabajo y dinero de elaborar que causa que el gremio de herreros tiemble solo con ser mencionada.<br><br>Esta espada es forjada con materiales bajo calor extremo. Se requieren llamas capaces de fundir cualquier metal casi al instante para poder fabricar esta espada, lo que hace que los artesanos que las elaboran deben soportar un calor extremo."]}, "accuracy": 0}