{"slot": "Weapon", "compendium_shown": true, "price_buy": 100000, "requirements": null, "name": "Chaos Blade", "type_id": 2, "skills": [221620], "is_twohanded": false, "rarity": 8, "compendium_id": 768, "dmg_variance": null, "slot_id": 1, "effects": ["Grants 'Dagger Cycle' passive."], "price_sell": 10000, "stats": {"status_inflict": null, "status_resist": null, "element_resist": null, "HP": 0, "ATK": 135, "element_inflict": null, "MP": 0, "MAG": 0, "SPR": 0, "DEF": 0}, "icon": "item_10240.png", "type": "Sword", "strings": {"name": ["Chaos Blade", "\u6df7\u6c8c\u4e4b\u528d", "\uce74\uc624\uc2a4 \ube14\ub808\uc774\ub4dc", "Lame du chaos", "Chaosklinge", "Hoja de tormento"], "desc_short": ["A sword used by a warrior from the Farplane.", "\u7570\u754c\u6b66\u4eba\u6240\u4f7f\u7528\u7684\u528d", "\uc774\uacc4\uc758 \ubb34\uc778\uc774 \uc0ac\uc6a9\ud558\ub358 \uac80.", "Une \u00e9p\u00e9e utilis\u00e9e par un guerrier originaire de l\u2019Au-del\u00e0.", "Ein Schwert eines Kriegers aus einer fernen Welt.", "Una espada que sol\u00eda usar un guerrero del Et\u00e9reo."], "desc_long": ["A sword brought from the faraway world of Ivalice. This sword was used by one of the judge masters, who led knights of authority belonging to the Arcadian Empire. This particular warrior fought holding a sword in each hand. One of it being the chaos blade, and the other a unique short sword.", "\u4f86\u81ea\u7570\u754c\u4f0a\u74e6\u5229\u65af\u7684\u528d\u3002\u5728\u963f\u723e\u5361\u8fea\u4e9e\u5e1d\u570b\u4e2d\uff0c\u638c\u7ba1\u53f8\u6cd5\u7684\u9a0e\u58eb\u5011\u4e4b\u7d71\u5e25\u300c\u6700\u9ad8\u5be9\u5224\u8005\u300d\u7684\u5176\u4e2d\u4e00\u4eba\u6240\u4f7f\u7528\u904e\u7684\u7269\u54c1\u3002\u4ed6\u4f3c\u4e4e\u5c07\u6df7\u6c8c\u4e4b\u528d\u914d\u5408\u77ed\u528d\u4f7f\u7528\uff0c\u4ee5\u4e8c\u5200\u6d41\u7684\u59ff\u614b\u6230\u9b25\u3002", "\uc774\uacc4 '\uc774\ubc1c\ub9ac\uc2a4'\uc5d0\uc11c \uc720\uc785\ub41c \uac80. \uc544\ub974\uce74\ub514\uc544 \uc81c\uad6d\uc758 \ubc95\uc744 \uad00\ub9ac\ud558\ub294 \uae30\uc0ac\ub4e4\uc744 \uc9c0\ud718\ud558\ub358 '\uc800\uc9c0 \ub9c8\uc2a4\ud130' \uc911 \ud558\ub098\uac00 \ud718\ub450\ub974\ub358 \uac83\uc774\ub77c \uc54c\ub824\uc838 \uc788\ub2e4. \uadf8\ub294 \uc774 \uce74\uc624\uc2a4 \ube14\ub808\uc774\ub4dc\uc640 \ub2e8\uac80\uc744 \uc870\ud569\ud55c \uc774\ub3c4\ub958\ub85c \uc804\ud22c\uc5d0 \uc784\ud588\ub2e4\uace0 \ud55c\ub2e4.", "Une \u00e9p\u00e9e rapport\u00e9e du monde lointain d\u2019Ivalice. Elle \u00e9tait utilis\u00e9e par l\u2019un des juges supr\u00eames qui \u00e9taient \u00e0 la t\u00eate des chevaliers appartenant \u00e0 l\u2019empire arcadien. Le guerrier en question brandissait deux \u00e9p\u00e9es ; une dans chaque main. L\u2019une de ces armes \u00e9tait une lame du chaos, tandis que l\u2019autre \u00e9tait une \u00e9p\u00e9e courte de conception unique.", "Ein Schwert aus der fernen Welt Ivalice. Dieses Schwert wurde von einem der Hohen Richter benutzt, welche die rechtsprechenden Ritter des Archadianischen Imperiums anf\u00fchrten. Der besagte Krieger k\u00e4mpfte mit einem Schwert in jeder Hand. Eines davon war die Chaosklinge, das andere ein Kurzschwert.", "Una espada que proviene del lejano mundo de Ivalice. Esta espada la us\u00f3 uno de los maestros jueces, personaje que lider\u00f3 a caballeros de renombre del Imperio de Arcadia. Este guerrero en particular luch\u00f3 blandiendo una espada en cada mano. Una de estas era la Hoja de tormento y la otra una espada corta muy especial."]}, "accuracy": 0}