{"slot": "Chest", "compendium_shown": true, "price_buy": 400, "requirements": null, "name": "Mage's Habit", "type_id": 50, "skills": null, "is_twohanded": false, "rarity": 4, "compendium_id": 151, "dmg_variance": null, "slot_id": 4, "effects": null, "price_sell": 40, "stats": {"status_inflict": null, "status_resist": null, "element_resist": null, "HP": 0, "ATK": 0, "element_inflict": null, "MP": 0, "MAG": 10, "SPR": 10, "DEF": 20}, "icon": "item_20102.png", "type": "Cloth", "strings": {"name": ["Mage's Habit", "\u9b54\u9053\u58eb\u670d", "\ub9c8\ub3c4\uc0ac\uc758 \uc637", "Manteau de mage", "Magierumhang", "Capa de mago"], "desc_short": ["Clothes that enhance magical powers.", "\u80fd\u63d0\u9ad8\u9b54\u529b\u7684\u8863\u670d", "\ub9c8\ub825\uc744 \ub192\uc774\ub294 \uc637", "V\u00eatement am\u00e9liorant les pouvoirs magiques.", "Kleidung, die magische Kr\u00e4fte verst\u00e4rkt.", "Ropa que aumenta el poder m\u00e1gico."], "desc_long": ["The power of magic depends greatly on its user. Therefore, a lot of mages train their hardest every day in order to strengthen themselves, even if only a little. The mage's habit is made of a specially woven fabric that heightens the magical powers and spirit of the wearer. However, since it can only amplify such qualities based on the wearer's current conditions, it would be wise not to overestimate its abilities.", "\u9b54\u6cd5\u7684\u5a01\u529b\u53d7\u9a45\u4f7f\u8005\u9b54\u529b\u7684\u5f71\u97ff\u3002\u6b63\u56e0\u5982\u6b64\uff0c\u9b54\u9053\u58eb\u5011\u65e5\u591c\u4ed8\u51fa\u52aa\u529b\uff0c\u4e00\u9ede\u4e00\u6ef4\u5730\u63d0\u9ad8\u81ea\u5df1\u7684\u529b\u91cf\u3002\u9019\u4ef6\u8863\u670d\u7531\u7d93\u904e\u7279\u6b8a\u5de5\u85dd\u88fd\u4f5c\u7684\u5e03\u6599\u7e54\u6210\uff0c\u5177\u6709\u63d0\u9ad8\u4f7f\u7528\u8005\u7684\u9b54\u529b\u548c\u7cbe\u795e\u529b\u91cf\u7684\u6548\u7528\u3002\u4f46\u662f\uff0c\u5b83\u57fa\u672c\u4e0a\u53ea\u80fd\u5728\u4f7f\u7528\u8005\u539f\u672c\u529b\u91cf\u4e4b\u4e0a\u767c\u63ee\u4e00\u5b9a\u7684\u8f14\u52a9\u4f5c\u7528\uff0c\u56e0\u6b64\u4e0d\u53ef\u904e\u5ea6\u4f9d\u8cf4\u3002", "\ub9c8\ubc95\uc758 \uc704\ub825\uc740 \uc0ac\uc6a9\uc790\uc758 \ub9c8\ub825\uc5d0 \ud06c\uac8c \uc88c\uc6b0\ub41c\ub2e4. \uadf8\ub798\uc11c \ub9c8\ub3c4\uc0ac\ub4e4\uc740 \uc870\uae08\uc774\ub77c\ub3c4 \ud798\uc744 \ub192\uc774\uae30 \uc704\ud574 \ubc24\ub0ae\uc73c\ub85c \ub178\ub825\ud55c\ub2e4. \uc774 \uc637\uc740 \ud2b9\uc218\ud55c \ucc9c\uc73c\ub85c \uc81c\uc791\ub418\uc5b4 \uc7a5\ucc29\uc790\uc758 \ub9c8\ub825\uacfc \uc815\uc2e0\ub825\uc744 \ub192\uc5ec\uc900\ub2e4. \ub2e8 \uc5b4\ub514\uae4c\uc9c0\ub098 \uc7a5\ucc29\uc790\uac00 \uc9c0\ub2cc \ubcf8\ub798\uc758 \ud798\uc744 \ubcf4\uc870\ud558\ub294 \uc218\uc900\uc5d0 \ubd88\uacfc\ud558\ub2c8 \uacfc\uc2e0\uc740 \uae08\ubb3c\uc774\ub2e4.", "La puissance de la magie d\u00e9pend beaucoup des qualit\u00e9s de son utilisateur. De nombreux mages redoublent donc d'efforts au quotidien pour se renforcer. Le manteau de mage, en tissu tress\u00e9, augmente l'esprit et le pouvoir magique. Son intensit\u00e9 d\u00e9pend cependant uniquement des aptitudes naturelles du porteur : mieux vaut ne pas surestimer son efficacit\u00e9.", "Die Wirksamkeit von Zauberspr\u00fcchen h\u00e4ngt stark von der inneren Magie ihrer Anwender ab. Viele Magier trainieren daher t\u00e4glich, um ihre Kraft so weit wie m\u00f6glich zu steigern. Das Magiergewand wird aus einem speziell gewobenen Stoff angefertigt, der die magische und psychische Kraft des Tr\u00e4gers verst\u00e4rkt. Dies h\u00e4ngt jedoch ma\u00dfgeblich von den bereits vorhandenen F\u00e4higkeiten ab \u2013 man sollte sich also nicht \u00fcbersch\u00e4tzen.", "El poder de la magia depende mucho de quien la usa. Por ello, muchos magos entrenan a fondo todos los d\u00edas para ser m\u00e1s fuertes, por poco que sea. La capa de mago est\u00e1 hecha con una fibra especial que potencia los poderes m\u00e1gicos y el esp\u00edritu de quien lo lleva. Sin embargo, dado que solo amplifica lo que ya existe, no deben sobrestimarse sus habilidades."]}, "accuracy": 0}