{"slot": "Chest", "compendium_shown": true, "price_buy": 50000, "requirements": null, "name": "Lordly Robe", "type_id": 53, "skills": [100710, 100720], "is_twohanded": false, "rarity": 7, "compendium_id": 315, "dmg_variance": null, "slot_id": 4, "effects": ["Grants 'Auto-Protect' passive.", "Grants 'Auto-Shell' passive."], "price_sell": 5000, "stats": {"status_inflict": null, "status_resist": null, "element_resist": null, "HP": 0, "ATK": 0, "element_inflict": null, "MP": 0, "MAG": 35, "SPR": 35, "DEF": 45}, "icon": "item_20413.png", "type": "Robe", "strings": {"name": ["Lordly Robe", "\u8cb4\u65cf\u6cd5\u888d", "\uc9c0\ubc30\uc790\uc758 \ub85c\ube0c", "Manteau royal", "F\u00fcrstenmantel", "Atuendo real"], "desc_short": ["A gorgeous robe worn by high priests.", "\u9ad8\u50e7\u7a7f\u6234\u7684\u8c6a\u83ef\u6cd5\u888d", "\uace0\uc2b9\uc774 \uac78\uce58\ub294 \ud638\ud654\ub85c\uc6b4 \ub85c\ube0c", "Manteau magnifique port\u00e9 par les pr\u00eatres.", "Eine pr\u00e4chtige Robe, die von Hohepriestern getragen wird.", "Atuendo los sumos sacerdotes."], "desc_long": ["A robe only given to a selected few elite of the clergy. Those who serve the gods are usually men and women of deep faith who pour their entire body and soul into their beliefs. Unfortunately, however, there was also a time when certain members of the clergy abused their power and did not hesitate on using it to obtain this precious robe. This action backfired though, as the robe will only show its true power to those true of heart.", "\u53ea\u6709\u5c45\u9ad8\u4f4d\u7684\u8056\u8077\u8005\u624d\u80fd\u7a7f\u8457\u7684\u6cd5\u888d\u3002\u8056\u8077\u8005\u5373\u6307\u5168\u8eab\u5fc3\u4f8d\u5949\u795e\u660e\u7684\u6e05\u5ec9\u4e4b\u4eba\u3002\u4f46\u5728\u4fe1\u4ef0\u7684\u529b\u91cf\u81a8\u8139\u7684\u6642\u4ee3\uff0c\u5076\u723e\u6703\u51fa\u73fe\u6c89\u6eba\u6b0a\u5229\u7684\u4eba\u3002\u9019\u985e\u4eba\u6703\u722d\u76f8\u8ffd\u6c42\u9019\u8eab\u6cd5\u888d\uff0c\u4f46\u6cd5\u888d\u6240\u5e36\u6709\u7684\u529b\u91cf\uff0c\u53ea\u6703\u70ba\u5167\u5fc3\u6e05\u6f54\u4e4b\u4eba\u767c\u63ee\u529f\u529b\u3002", "\uc120\ud0dd\ubc1b\uc740 \uace0\uc704 \uc131\uc9c1\uc790\ub9cc\uc774 \ub450\ub97c \uc218 \uc788\ub294 \ub85c\ube0c. \uc131\uc9c1\uc790\ub780 \uc2e0\uc5d0\uac8c \uc790\uc2e0\uc744 \ubc14\uce5c, \ubab8\ub3c4 \ub9c8\uc74c\ub3c4 \uccad\ub834\ud55c \uc0ac\ub78c\uc744 \ub9d0\ud558\uc9c0\ub9cc \uc2e0\uc559\uc774 \ud070 \ud798\uc744 \uac00\uc9c0\ub294 \uc2dc\ub300\uc5d0\ub294 \ub54c\ub85c \uad8c\ub825\uc5d0 \ub208\uc774 \uba3c \uc790\ub4e4\ub3c4 \ub098\ud0c0\ub09c\ub2e4. \uadf8\uc790\ub4e4\uc740 \ud558\ub098\uac19\uc774 \uc774 \ub85c\ube0c\ub97c \uac00\uc9c0\uace0 \uc2f6\uc5b4 \ud558\uc9c0\ub9cc, \ub85c\ube0c\uc5d0 \uae43\ub4e0 \uc9c4\uc815\ud55c \ud798\uc740 \uae68\ub057\ud55c \ub9c8\uc74c\uc744 \uac00\uc9c4 \uc0ac\ub78c\uc774 \ub458\ub800\uc744 \ub54c\ub9cc \ubc1c\ud718\ub41c\ub2e4\uace0 \ud55c\ub2e4.", "Un manteau offert uniquement \u00e0 une certaine \u00e9lite du clerg\u00e9. Ceux qui servent les dieux sont souvent des hommes et des femmes \u00e0 la foi in\u00e9branlable, qui se d\u00e9vouent corps et \u00e2me \u00e0 leurs croyances. H\u00e9las, il arriva un jour qu'un membre du clerg\u00e9 abusa de son pouvoir et l'utilisa pour s'emparer de ce pr\u00e9cieux v\u00eatement. Ce m\u00e9fait ne fut toutefois pas sans cons\u00e9quence, car le manteau ne montre son vrai pouvoir qu'\u00e0 celui ou celle dont le c\u0153ur est pur.", "Diese Robe wird nur besonders verdienstvollen Mitgliedern des Klerus' verliehen. Die Diener der G\u00f6tter sind normalerweise M\u00e4nner und Frauen von gro\u00dfer Fr\u00f6mmigkeit, die sich mit Leib und Seele ihrem Glauben hingeben. Leider kam es auch schon vor, dass weniger makellose Kleriker ihre Macht missbrauchten, um in den Besitz dieser Robe zu gelangen. Solche Bestrebungen sind jedoch immer zum Scheitern verurteilt, da die Robe ihre Kraft nur w\u00fcrdigen Tr\u00e4gern verleiht.", "Atuendo otorgado \u00fanicamente a la \u00e9lite del clericato. Aquellos que sirven a los dioses suelen ser hombres y mujeres que dedican cuerpo y alma a sus creencias. Desgraciadamente, hubo un tiempo en el que algunos miembros de la clerec\u00eda abusaban de su poder, us\u00e1ndolo sin vacilar para conseguir este preciado atuendo. Sin embargo, la estrategia no les funcion\u00f3, ya que esta t\u00fanica s\u00f3lo muestra su forma real a los puros de coraz\u00f3n."]}, "accuracy": 0}