{"TMR": ["EQUIP", 403043800], "name": "Lotus Mage Fina", "is_summonable": true, "skills": [{"level": 1, "type": "ABILITY", "id": 100020, "rarity": 5}, {"level": 1, "type": "ABILITY", "id": 200470, "rarity": 5}, {"level": 1, "type": "MAGIC", "id": 20190, "rarity": 5}, {"level": 1, "type": "MAGIC", "id": 10010, "rarity": 5}, {"level": 7, "type": "ABILITY", "id": 221160, "rarity": 5}, {"level": 7, "type": "MAGIC", "id": 10190, "rarity": 5}, {"level": 16, "type": "ABILITY", "id": 221010, "rarity": 5}, {"level": 16, "type": "MAGIC", "id": 10200, "rarity": 5}, {"level": 23, "type": "ABILITY", "id": 213310, "rarity": 5}, {"level": 23, "type": "MAGIC", "id": 10180, "rarity": 5}, {"level": 31, "type": "ABILITY", "id": 221130, "rarity": 5}, {"level": 40, "type": "ABILITY", "id": 221140, "rarity": 5}, {"level": 47, "type": "ABILITY", "id": 221020, "rarity": 5}, {"level": 55, "type": "ABILITY", "id": 221030, "rarity": 5}, {"level": 69, "type": "ABILITY", "id": 221090, "rarity": 5}, {"level": 80, "type": "ABILITY", "id": 200150, "rarity": 5}, {"level": 1, "type": "ABILITY", "id": 100180, "rarity": 6}, {"level": 9, "type": "MAGIC", "id": 10230, "rarity": 6}, {"level": 17, "type": "MAGIC", "id": 10290, "rarity": 6}, {"level": 28, "type": "ABILITY", "id": 221150, "rarity": 6}, {"level": 37, "type": "ABILITY", "id": 100120, "rarity": 6}, {"level": 45, "type": "ABILITY", "id": 221100, "rarity": 6}, {"level": 56, "type": "ABILITY", "id": 221050, "rarity": 6}, {"level": 61, "type": "ABILITY", "id": 221110, "rarity": 6}, {"level": 72, "type": "ABILITY", "id": 221070, "rarity": 6}, {"level": 84, "type": "ABILITY", "id": 221080, "rarity": 6}, {"level": 92, "type": "ABILITY", "id": 204350, "rarity": 6}, {"level": 92, "type": "MAGIC", "id": 20440, "rarity": 6}, {"level": 100, "type": "ABILITY", "id": 221060, "rarity": 6}], "sex_id": 2, "entries": {"100011806": {"growth_pattern": 30, "status_resist": [0, 0, 0, 0, 0, 0, 0, 0], "element_resist": [0, 0, 0, 0, 0, 0, 0, 0], "stats": {"HP": [1114, 3376, 450], "ATK": [37, 112, 30], "MP": [67, 204, 75], "MAG": [47, 141, 30], "SPR": [51, 156, 30], "DEF": [38, 114, 30]}, "magic_affinity": [8, 8, 5, 0], "ability_slots": 4, "limitburst_id": 100011806, "attack_count": 33, "magical_resist": 0, "awakening": null, "rarity": 6, "compendium_id": 816, "attack_damage": [[33, 33, 34]], "max_lb_drop": 4, "physical_resist": 0, "attack_frames": [72, 96, 120], "effect_frames": [70, 94, 118], "strings": {"evolution": ["What power...<br>I owe this power to you,<br>so please use it as you will!", "\u597d\u5f37\u5927\u7684\u529b\u91cf\u2026\u2026<br>\u591a\u8667\u4e86\u5927\u5bb6\u6211\u624d\u80fd\u5920\u8b8a\u5f37\uff0c<br>\u6211\u5fc5\u9808\u4ee5\u9019\u4efd\u529b\u91cf\u56de\u5831\u5927\u5bb6\u624d\u884c\u3002", "\uad49\uc7a5\ud55c \ud798\uc774\uc57c\u2026\u2026<br>\ubaa8\ub450\uc758 \ub355\ubd84\uc5d0 \uac15\ud574\uc9c4 \uac70\ub2c8\uae4c<br>\uc774 \ud798\uc73c\ub85c \ubcf4\ub2f5\ud574 \uc918\uc57c\uaca0\uc9c0.", "Quelle puissance...<br>Je vous dois cette force,<br>utilisez-la comme bon vous semble\u00a0!", "Was  f\u00fcr eine Kraft ...<br>Nur euch habe ich diese St\u00e4rke zu verdanken, also benutzt sie, so viel ihr wollt!", "Qu\u00e9 poder...<br>Te debo este poder,<br>\u00a1as\u00ed que \u00fasalo como te parezca!"], "affinity": ["Your feelings make me stronger.<br>Please, accept my feelings for you, too.<br>This should be of help to you.", "\u4f60\u7684\u300c\u5fc3\u610f\u300d\u8b93\u6211\u8b8a\u5f97\u66f4\u52a0\u5f37\u5927\u3002<br>\u9019\u6b21\u8acb\u4f60\u4e5f\u63a5\u53d7\u6211\u7684\u5fc3\u610f\u3002<br>\u6211\u76f8\u4fe1\u4e00\u5b9a\u6703\u6210\u70ba\u652f\u6301\u4f60\u7684\u529b\u91cf\u3002", "\ub124 \ub9c8\uc74c\uc774 \ub0a0 \uac15\ud558\uac8c \ud574.<br>\uc774\ubc88\uc5d4 \ub0b4 \ub9c8\uc74c\uc744 \ubc1b\uc544\uc918.<br>\ubd84\uba85 \ub124 \ud798\uc774 \ub420 \uac70\uc57c.", "Vos \u00e9motions me rendent plus forte.<br>Je vous en prie, acceptez ces m\u00eames sentiments de ma part.<br>\u00c7a devrait vous aider.", "Deine Gedanken machen mich st\u00e4rker.<br>Bitte nimm auch meine Gedanken an dich an.<br>Sicher werden sie dir auch Kraft geben.", "Tus sentimientos me hacen m\u00e1s fuerte.<br>Por tanto, acepta t\u00fa tambi\u00e9n lo que yo siento hacia ti.<br>Eso deber\u00eda ayudarte."], "description": ["A white mage gifted with the ability to open the hearts of many with her kindness. Although in the beginning Fina's memory loss had prompted her to act much like a child, she has matured with time. Now she even cooks meals for her companions, her specialty being fried eggs. Following Rain's disappearance, she is absolutely determined to find him with Lasswell's help.", "\u4e0d\u8ad6\u8207\u8ab0\u90fd\u80fd\u6253\u6210\u4e00\u7247\uff0c\u5167\u5fc3\u6eab\u67d4\u7684\u5973\u6027\u9b54\u9053\u58eb\u3002\u96d6\u7136\u6700\u521d\u56e0\u70ba\u8a18\u61b6\u55aa\u5931\u7684\u5f71\u97ff\uff0c\u884c\u70ba\u50cf\u500b\u5c0f\u5b69\u5b50\uff0c\u4f46\u662f\u73fe\u5728\u5df2\u7d93\u6210\u9577\u5230\u80fd\u66ff\u5925\u4f34\u5011\u88fd\u4f5c\u6599\u7406\uff0c\u64c5\u9577\u7684\u6599\u7406\u662f\u8377\u5305\u86cb\u3002\u96d6\u7136\u9084\u662f\u4f9d\u9760\u8457\u62c9\u65af\u97cb\u723e\uff0c\u4f46\u662f\u95dc\u65bc\u5c0b\u627e\u96f7\u56e0\u9019\u4ef6\u4e8b\u60c5\uff0c\u5979\u537b\u62b1\u6301\u8457\u4e0d\u80fd\u8f38\u7d66\u5176\u4ed6\u4eba\u7684\u5fc3\u614b\u3002", "\ub204\uad6c\uc5d0\uac8c\ub098 \ub9c8\uc74c\uc744 \ud130\ub193\uace0 \ub300\ud558\ub294, \uc0c1\ub0e5\ud55c \ub9c8\uc74c\uc528\ub97c \uac00\uc9c4 \ub9c8\ub3c4\uc0ac \uc18c\ub140. \ucc98\uc74c \ub9cc\ub0ac\uc744 \ub54c\uc5d0\ub294 \uae30\uc5b5 \uc0c1\uc2e4\ub85c \uc778\ud574 \uc5b4\ub9b0\uc544\uc774\ub098 \ub2e4\ub984\uc5c6\uc5c8\uc9c0\ub9cc, \uc9c0\uae08\uc740 \ubaa8\ub450\ub97c \uc704\ud574 \uc694\ub9ac\ub97c \ub9cc\ub4e4\uc5b4 \ub300\uc811\ud574\uc904 \uc815\ub3c4\ub85c \uc131\uc7a5\ud588\ub2e4. \uac00\uc7a5 \uc798 \ud558\ub294 \uc694\ub9ac\ub294 \ub2ec\uac40 \ud504\ub77c\uc774\ub85c, \ub77c\uc2a4\uc6f0\uc744 \uc758\uc9c0\ud558\uace0 \uc788\uc9c0\ub9cc \ub808\uc778\uc744 \ucc3e\ub294 \uc77c\uc5d0 \uad00\ud574\uc11c \ub9cc\ud07c\uc740 \uc9c0\uace0 \uc2f6\uc9c0 \uc54a\uc740 \ub9c8\uc74c\uc744 \ud488\uace0 \uc788\ub2e4.", "Un mage blanc poss\u00e9dant la facult\u00e9 d'ouvrir le c\u0153ur de nombreux hommes et femmes par sa bont\u00e9. Au commencement, Fina, victime de sa perte de m\u00e9moire, se comportait souvent comme une enfant. Elle finit cependant par m\u00fbrir avec le temps. \u00c0 pr\u00e9sent, elle se charge m\u00eame de cuisiner pour ses compagnons et pr\u00e9pare souvent des \u0153ufs au plat, sa sp\u00e9cialit\u00e9. Rain ayant disparu, elle est plus que jamais d\u00e9termin\u00e9e \u00e0 le retrouver, et ce, avec l'aide de Lasswell.", "Eine Wei\u00dfmagierin, die \u00fcber die Gabe verf\u00fcgt, Herzen mit ihrer G\u00fcte zu \u00f6ffnen. Obwohl ihr Ged\u00e4chtnisverlust dazu f\u00fchrte, dass sie sich anfangs oft wie ein Kind verhielt, ist sie in kurzer schnell herangereift und kocht inzwischen sogar Mahlzeiten f\u00fcr die ganze Gruppe. Ihre Spezialit\u00e4t sind Brateier. Sie ist fest dazu entschlossen, nicht zu ruhen, ehe sie Rain mit Lasswells Hilfe gefunden hat.", "Una maga blanca cuya bondad es tan grande que ablanda el coraz\u00f3n de la gente. Aunque al principio la p\u00e9rdida de memoria de Fina la hac\u00eda actuar de una forma un tanto infantil, con el paso del tiempo ha conseguido madurar. Ahora, incluso cocina para sus compa\u00f1eros; de hecho, su especialidad son los huevos fritos. Por otra parte, tras la desaparici\u00f3n de Rain, Fina, con la ayuda de Lasswell, est\u00e1 completamente volcada en la tarea de encontrarlo."], "fusion": ["I don't want anyone to be sad anymore.<br>That is why I will get stronger and stronger.", "\u6211\u4e0d\u60f3\u518d\u8b93\u4efb\u4f55\u4eba\u611f\u5230\u60b2\u50b7\u3002<br>\u6240\u4ee5\uff0c\u6211\u4e00\u5b9a\u8981\u8b8a\u5f97\u66f4\u5f37\u3002", "\uadf8 \ub204\uad6c\ub3c4 \uc2ac\ud37c\ud558\uc9c0 \uc54a\uc558\uc73c\uba74 \uc88b\uaca0\uc5b4.<br>\uadf8\ub7ec\ub2c8\uae4c \ub09c \ub354\uc6b1\ub354 \uac15\ud574\uc9c8 \uac70\uc57c.", "Je ne veux plus de tristesse.<br>C'est pourquoi je compte me surpasser encore et encore.", "Ich will nicht mehr traurig sein.<br> Deswegen werde ich nun st\u00e4rker und st\u00e4rker.", "No quiero que nadie se ponga triste.<br>Por eso, mi objetivo es estar m\u00e1s y m\u00e1s fuerte."], "summon": ["To think, my feelings toward everyone could take such a form. Being a vision sure is wonderful.", "\u5c0d\u5927\u5bb6\u7684\u5fc3\u610f\u80fd\u8b8a\u6210\u9019\u7a2e\u5f62\u5f0f\u3002\u5e7b\u5175\u53ef\u771f\u662f\u53b2\u5bb3\u5440\u3002", "\ubaa8\ub450\ub97c \ud5a5\ud55c \ub9c8\uc74c\uc774, \uc774\ub807\uac8c \ud615\ud0dc\ub97c \ube5a\uc740 \uac70\uc57c.<br>\ube44\uc804\uc774\ub780 \uc815\ub9d0 \uba4b\uc9c0\uad6c\ub098.", "Difficile de croire que mes sentiments \u00e0 l'encontre de vous tous pouvaient prendre une telle forme. \u00catre une vision a ses avantages.", "Dass meine Gef\u00fchle f\u00fcr alle, so eine Form annehmen k\u00f6nnen...!<br>Visionen sind etwas Wundervolles.", "Y pensar que los sentimientos que profeso hacia alguien podr\u00edan tomar esa forma. Desde luego, no me puedo quejar de ser una visi\u00f3n."]}}, "100011805": {"growth_pattern": 30, "status_resist": [0, 0, 0, 0, 0, 0, 0, 0], "element_resist": [0, 0, 0, 0, 0, 0, 0, 0], "stats": {"HP": [780, 2364, 300], "ATK": [26, 79, 20], "MP": [47, 143, 50], "MAG": [33, 99, 20], "SPR": [36, 110, 20], "DEF": [26, 80, 20]}, "magic_affinity": [7, 7, 4, 0], "ability_slots": 4, "limitburst_id": 100011805, "attack_count": 33, "magical_resist": 0, "awakening": {"gil": 4000, "materials": {"290060300": 10, "290060000": 10, "290060100": 5, "290050500": 5, "290060400": 20}}, "rarity": 5, "compendium_id": 815, "attack_damage": [[33, 33, 34]], "max_lb_drop": 4, "physical_resist": 0, "attack_frames": [72, 96, 120], "effect_frames": [70, 94, 118], "strings": {"evolution": [null, null, null, null, null, null], "affinity": ["Your feelings make me stronger.<br>Please, accept my feelings for you, too.<br>This should be of help to you.", "\u4f60\u7684\u300c\u5fc3\u610f\u300d\u8b93\u6211\u8b8a\u5f97\u66f4\u52a0\u5f37\u5927\u3002<br>\u9019\u6b21\u8acb\u4f60\u4e5f\u63a5\u53d7\u6211\u7684\u5fc3\u610f\u3002<br>\u6211\u76f8\u4fe1\u4e00\u5b9a\u6703\u6210\u70ba\u652f\u6301\u4f60\u7684\u529b\u91cf\u3002", "\ub124 \ub9c8\uc74c\uc774 \ub0a0 \uac15\ud558\uac8c \ud574.<br>\uc774\ubc88\uc5d4 \ub0b4 \ub9c8\uc74c\uc744 \ubc1b\uc544\uc918.<br>\ubd84\uba85 \ub124 \ud798\uc774 \ub420 \uac70\uc57c.", "Vos \u00e9motions me rendent plus forte.<br>Je vous en prie, acceptez ces m\u00eames sentiments de ma part.<br>\u00c7a devrait vous aider.", "Deine Gedanken machen mich st\u00e4rker.<br>Bitte nimm auch meine Gedanken an dich an.<br>Sicher werden sie dir auch Kraft geben.", "Tus sentimientos me hacen m\u00e1s fuerte.<br>Por tanto, acepta t\u00fa tambi\u00e9n lo que yo siento hacia ti.<br>Eso deber\u00eda ayudarte."], "description": ["A white mage traveling with Lasswell. Fina lost a great part of her memories after having been sealed within a crystal  for hundreds of years. However, she managed to eventually come into her own upon meeting Rain, Lasswell, and a multitude of other people. She loves petting chocobos, so when there are none around for her to coddle, she satisfies herself with petting Lid's Mechabo instead.", "\u8207\u62c9\u65af\u97cb\u723e\u4e00\u8d77\u65c5\u884c\u7684\u5973\u6027\u9b54\u9053\u58eb\u3002\u56e0\u70ba\u53d7\u5230\u6c34\u6676\u5c01\u5370\u7684\u5f71\u97ff\uff0c\u5931\u53bb\u4e86\u5927\u90e8\u5206\u7684\u8a18\u61b6\u3002\u4f46\u662f\u5728\u9047\u898b\u96f7\u56e0\u8207\u62c9\u65af\u97cb\u723e\u7b49\u4eba\u5f8c\uff0c\u81ea\u8eab\u4e5f\u6709\u6240\u6210\u9577\u3002\u975e\u5e38\u559c\u6b61\u64ab\u6478\u9678\u884c\u9ce5\uff0c\u7576\u5468\u570d\u6c92\u6709\u9678\u884c\u9ce5\u7684\u6642\u5019\uff0c\u5c31\u6703\u5c07\u91cc\u5fb7\u7684\u6a5f\u68b0\u9678\u884c\u9ce5\u7576\u6210\u4ee3\u66ff\u54c1\u3002", "\ub77c\uc2a4\uc6f0\uacfc \ud568\uaed8 \uc5ec\ud589\ud558\ub294 \ub9c8\ub3c4\uc0ac \uc18c\ub140. \ud06c\ub9ac\uc2a4\ud0c8\uc5d0 \ubd09\uc778\ub418\uc5b4 \uc788\uc5c8\ub358 \ud0d3\uc5d0 \uae30\uc5b5 \ub300\ubd80\ubd84\uc744 \uc783\uc5b4\ubc84\ub838\uc9c0\ub9cc, \ub808\uc778\uacfc \ub77c\uc2a4\uc6f0, \uadf8\ub9ac\uace0 \uc5ec\ub7ec \uc0ac\ub78c\uacfc\uc758 \ub9cc\ub0a8\uc744 \ud1b5\ud574 \uc131\uc7a5\ud588\ub2e4. \ucd08\ucf54\ubcf4\ub97c \uc4f0\ub2e4\ub4ec\ub294 \uac83\uc744 \uac00\uc7a5 \uc88b\uc544\ud558\uba70, \uc8fc\ubcc0\uc5d0 \ucd08\ucf54\ubcf4\uac00 \uc5c6\uc744 \ub54c\ub294 \ub9ac\ub4dc\uc758 \uba54\uce74\ubcf4\ub97c \ub300\uc2e0 \uc4f0\ub2e4\ub4ec\uae30\ub3c4 \ud55c\ub2e4.", "Un mage blanc voyageant au c\u00f4t\u00e9 de Lasswell. Fina fut scell\u00e9e \u00e0 l'int\u00e9rieur d'un cristal des si\u00e8cles durant, ce qui provoqua chez elle une perte de la m\u00e9moire. C'est en rencontrant Rain, Lasswell et bien d'autres qu'elle parvint, au fil du temps, \u00e0 retrouver sa propre personnalit\u00e9. Elle adore caresser les chocobos. Ainsi, quand elle n'en trouve aucun dans les environs, elle comble ce manque en cajolant le M\u00e9cabo de Lid.", "Eine Wei\u00dfmagierin, die mit Lasswell reist. Dass sie in einem Kristall versiegelt war, hatte Auswirkungen auf ihr Ged\u00e4chtnis und so musste sie feststellen, dass ein Gro\u00dfteil ihrer Erinnerungen verlorenging. Nachdem sie aber auf Rain, Lasswell und viele andere traf, reifte sie erneut heran. Sie liebt es, Chocobos zu streicheln; wenn weit und breit keine Chocobos anzutreffen sind, begn\u00fcgt sie sich damit, Lids Mechabo zu streicheln.", "Una maga blanca que viaja con Lasswell. Fina perdi\u00f3 la mayor parte de su memoria tras permanecer sellada en un cristal durante siglos. Sin embargo, consigui\u00f3 volver en s\u00ed cuando conoci\u00f3 a Rain, Lasswell y a otra multitud de gente. A Fina le encanta acariciar chocobos, por lo que, cuando no hay ninguno cerca, se entretiene jugueteando con el chocobot de Lid."], "fusion": ["I have become stronger.<br>Surely now I will be of<br>better use to everyone.", "\u6211\uff0c\u8b8a\u5f37\u4e86\u3002<br>\u9019\u6a23\u7684\u8a71\u4e00\u5b9a\u2026\u2026<br>\u80fd\u5e6b\u5f97\u4e0a\u5fd9\u4e86\u5427\u3002", "\ub098, \uac15\ud574\uc9c4 \uac70\uc9c0.<br>\uc9c0\uae08\uc774\ub77c\uba74 \ubd84\uba85\u2026\u2026<br>\ubaa8\ub450\uc758 \ud798\uc774 \ub420 \uc218 \uc788\uc744 \uac70\uc57c.", "J'ai gagn\u00e9 en puissance.<br>Il est certain qu'\u00e0 pr\u00e9sent, je saurai<br>\u00eatre plus utile \u00e0 mes proches.", "Ich bin st\u00e4rker geworden.<br> Nun werde ich euch bestimmt eine gr\u00f6\u00dfere Hilfe sein k\u00f6nnen.", "Me he vuelto m\u00e1s fuerte.<br>Ahora puedo hacer<br>mucho m\u00e1s por la gente."], "summon": ["I am Fina.<br>I will do my best to work with everyone, so let's all do our best!", "\u6211\u662f\u83f2\u5a1c\u3002<br>\u6211\u6703\u70ba\u4e86\u5927\u5bb6\u800c\u52aa\u529b\u7684\u3002\u8acb\u591a\u6307\u6559\uff01", "\ub098\ub294 \ud53c\ub098\uc57c!<br>\ubaa8\ub450\ub97c \uc704\ud574 \ucd5c\uc120\uc744 \ub2e4\ud560 \ud14c\ub2c8\uae4c<br>\uc798 \ubd80\ud0c1\ud574!", "Je suis Fina.<br>Je ferai de mon mieux pour travailler avec vous tous, alors allons-y de bon c\u0153ur\u00a0!", "Ich bin Fina.<br>Ich werde mein Bestes geben, um mit euch zusammenzuarbeiten!", "Soy Fina.<br>\u00a1Lo har\u00e9 lo mejor que pueda para colaborar con todo el mundo! \u00a1La uni\u00f3n hace la fuerza!"]}}}, "job": "Mage", "sex": "Female", "game": "FFBE", "rarity_max": 6, "names": ["Lotus Mage Fina", "\u767d\u84ee\u9b54\u9053\u58eb\u83f2\u5a1c", "\ubc31\ub828\uc758 \ub9c8\ub3c4\uc0ac \ud53c\ub098", "Fina, mage du lotus", "Lotusmagierin Fina", "Fina maga del loto"], "equip": [5, 6, 7, 12, 15, 40, 50, 53, 60], "game_id": 11001, "rarity_min": 5, "tribe_id": 5, "id": "100011805", "job_id": 19}