{"TMR": ["MATERIA", 504211290], "name": "Moogle", "is_summonable": false, "skills": [{"level": 1, "type": "MAGIC", "id": 10090, "rarity": 4}, {"level": 1, "type": "MAGIC", "id": 10140, "rarity": 4}, {"level": 1, "type": "MAGIC", "id": 10020, "rarity": 4}, {"level": 20, "type": "ABILITY", "id": 211210, "rarity": 4}, {"level": 20, "type": "ABILITY", "id": 211190, "rarity": 4}, {"level": 20, "type": "ABILITY", "id": 211200, "rarity": 4}, {"level": 25, "type": "ABILITY", "id": 100130, "rarity": 4}, {"level": 35, "type": "ABILITY", "id": 100160, "rarity": 4}, {"level": 60, "type": "ABILITY", "id": 211280, "rarity": 4}, {"level": 5, "type": "ABILITY", "id": 101350, "rarity": 5}, {"level": 10, "type": "MAGIC", "id": 10070, "rarity": 5}, {"level": 10, "type": "ABILITY", "id": 211220, "rarity": 5}, {"level": 40, "type": "ABILITY", "id": 211230, "rarity": 5}, {"level": 45, "type": "ABILITY", "id": 100100, "rarity": 5}, {"level": 65, "type": "ABILITY", "id": 100070, "rarity": 5}, {"level": 70, "type": "ABILITY", "id": 211240, "rarity": 5}, {"level": 80, "type": "MAGIC", "id": 10110, "rarity": 5}, {"level": 80, "type": "ABILITY", "id": 211300, "rarity": 5}, {"level": 1, "type": "ABILITY", "id": 211170, "rarity": 6}, {"level": 15, "type": "ABILITY", "id": 100040, "rarity": 6}, {"level": 30, "type": "MAGIC", "id": 10160, "rarity": 6}, {"level": 30, "type": "ABILITY", "id": 211270, "rarity": 6}, {"level": 50, "type": "ABILITY", "id": 211260, "rarity": 6}, {"level": 55, "type": "ABILITY", "id": 100010, "rarity": 6}, {"level": 75, "type": "ABILITY", "id": 101430, "rarity": 6}, {"level": 90, "type": "ABILITY", "id": 211250, "rarity": 6}, {"level": 100, "type": "ABILITY", "id": 211180, "rarity": 6}], "sex_id": 0, "entries": {"100008804": {"growth_pattern": 30, "status_resist": [0, 0, 0, 0, 0, 0, 0, 0], "element_resist": [0, 0, 0, 0, 0, 0, 0, 0], "stats": {"HP": [556, 1686, 240], "ATK": [28, 85, 16], "MP": [30, 90, 40], "MAG": [21, 63, 16], "SPR": [23, 70, 16], "DEF": [21, 63, 16]}, "magic_affinity": [5, 0, 0, 0], "ability_slots": 3, "limitburst_id": 100008804, "attack_count": 100, "magical_resist": 0, "awakening": {"gil": 2500, "materials": {"290031000": 13, "290020700": 25, "290050300": 15, "290050400": 8, "290030900": 8}}, "rarity": 4, "compendium_id": 586, "attack_damage": [[100]], "max_lb_drop": 8, "physical_resist": 0, "attack_frames": [70], "effect_frames": [68], "strings": {"evolution": [null, null, null, null, null, null], "affinity": ["It's been a fun adventure with you, kupo!<br>I wish to give you this bubbly feeling as proof of our friendship, kupo.", "\u80fd\u8207\u4f60\u4e00\u8d77\u5192\u96aa\u771f\u662f\u592a\u9ad8\u8208\u4e86\uff0c\u5eab\u5575\uff01<br>\u7c21\u76f4\u60f3\u8981\u628a\u83ab\u53e4\u5229\u7684\u7d68\u7403<br>\u7576\u4f5c\u53cb\u60c5\u7684\u8b49\u660e\u9001\u7d66\u4f60\uff0c\u5eab\u5575\u3002", "\ub108\uc640 \ud568\uaed8 \ubaa8\ud5d8\ud560 \uc218 \uc788\uc5b4\uc11c \uae30\ubed0\ucfe0\ud3ec!<br>\uc6b0\uc815\uc758 \uc99d\uac70\ub85c, \ubaa8\uadf8\uc758 \ud3fc\ud3fc\uc744<br>\uc120\ubb3c\ud558\uace0 \uc2f6\uc744 \uc815\ub3c4\ucfe0\ud3ec.", "Nous avons v\u00e9cu une incroyable aventure ensemble, kupo !<br>J'aimerais te donner mon pompon comme gage de notre amiti\u00e9, kupo.", "Es macht Spa\u00df, Abenteuer mit dir zu erleben, kupo!<br>Nimm dieses Sprudeln als Zeichen unserer Freundschaft, kupo.", "\u00a1Ha sido una aventura muy divertida, kup\u00f3!<br>Como prueba de nuestra amistad, \u00a1te dejo este cosquilleo, kup\u00f3!"], "description": ["A moogle that serves King Mog in the Farplane, kupo! If you haven't heard, this moogle is a brave soul that has defeated many an enemy within the walls of the castle. An admirable warrior indeed, kupo! Moogles may be small and cute, but they hide tremendous and unimaginable power... You don't believe me? It's true, kupo!", "\u5728\u7570\u754c\u7684\u57ce\u5821\u88e1\u4f8d\u5949\u83ab\u53e4\u5229\u738b\u7684\u83ab\u53e4\u5229\u5eab\u5575\uff01\u4e0d\u779e\u4f60\u8aaa\uff0c\u9023\u8a0e\u4f10\u904e\u8a31\u591a\u9b54\u7269\u7684\u52c7\u58eb\u90fd\u656c\u4f69\u83ab\u53e4\u5eab\u5575\u3002\u83ab\u53e4\u96d6\u7136\u5916\u578b\u5341\u5206\u5b0c\u5c0f\uff0c\u4f46\u6709\u8457\u8b93\u4eba\u96e3\u4ee5\u60f3\u50cf\u7684\u6050\u6016\u529b\u91cf\u5eab\u5575\uff01\u96e3\u9053\uff0c\u4f60\u5728\u61f7\u7591\u83ab\u53e4\u8aaa\u7684\u8a71\u55ce\u5eab\u5575\uff1f\u662f\u771f\u7684\u5eab\u5575\uff01", "\uc774\uacc4\uc758 \uc131\uc5d0\uc11c \ubaa8\uadf8\ub9ac \uc655\uc744 \ubaa8\uc2dc\ub294 \ubaa8\uadf8\ub9ac\ucfe0\ud3ec! \ubaa8\uadf8\ub294 \ub9d0\uc774\uc9c0, \uc131\uc5d0\uc11c \uc628\uac16 \ub9c8\ubb3c\ub4e4\uc744 \ucc98\uce58\ud574 \uc628 \uc6a9\uc0ac\ub85c\uc11c \ub9e4\uc6b0 \ub6f0\uc5b4\ub09c \uc874\uc7ac\ucfe0\ud3ec. \uadf8\uc57c \ubaa8\uadf8\uac00 \uc880 \uc870\uadf8\ub9e3\uae34 \ud558\uc9c0\ub9cc, \uac89\ubcf4\uae30\ub9cc\uc73c\ub860 \uc0c1\uc0c1\uc870\ucc28 \ud560 \uc218 \uc5c6\ub294 \ubb34\uc2dc\ubb34\uc2dc\ud55c \ud798\uc744 \uc228\uae30\uace0 \uc788\ub2e4\ucfe0\ud3ec! \u2026\u2026\uc124\ub9c8, \ubaa8\uadf8\uac00 \ud558\ub294 \ub9d0 \ubabb \ubbff\uc5b4\ucfe0\ud3ec? \uc9c4\uc9dc\uc57c\ucfe0\ud3ec!", "Un mog au service du roi Mog dans l'Au-del\u00e0, kupo\u00a0! Au cas o\u00f9 vous ne le saviez pas, ce mog est un brave guerrier qui a vaincu des myriades d\u2019ennemis dans l\u2019enceinte des murs du ch\u00e2teau. Un admirable combattant, pour s\u00fbr, kupo\u00a0! Les mogs sont petits et mignons, mais ils poss\u00e8dent une force presque inimaginable... Vous ne me croyez pas\u00a0? C\u2019est la v\u00e9rit\u00e9, kupo\u00a0!", "Ein Mogry, der dem Mogryk\u00f6nig im Schloss einer fernen Welt dient, kupo! Jetzt mal unter uns: Dieser Mogry ist ein echter Veteran, der schon so manches Monster im Schloss zu Fall gebracht hat. Eine Gefahr, mit der man rechnen sollte, kupo. So klein Mogrys auch sind, in ihnen verbergen sich unvorstellbar enorme Kr\u00e4fte, kupo! \u2026 Du zweifelst an meinen Worten, kupo? Ich sage die Wahrheit, kupoo!", "\u00a1Un moguri que sirve al Rey moguri en el Et\u00e9reo, kup\u00f3! En caso de que no lo sepas, este moguri es un valiente guerrero que derrot\u00f3 a decenas de enemigos dentro de las murallas del castillo. \u00a1Un guerrero digno de admiraci\u00f3n, kup\u00f3! Puede que los moguris parezcan peque\u00f1os y adorables, pero dentro de ellos reside un poder inimaginable... \u00bfNo me crees? \u00a1Es verdad, kup\u00f3!"], "fusion": ["With power like this,<br>it doesn't matter what kind of monster it is,<br>I'm not scared, kupo!", "\u53ea\u8981\u6709\u9019\u80a1\u529b\u91cf\uff0c<br>\u4e0d\u8ad6\u662f\u4ec0\u9ebc\u9b54\u7269<br>\u90fd\u4e0d\u5bb3\u6015\uff0c\u5eab\u5575\uff01", "\uc774 \ud798\uc774 \uc788\uc73c\uba74,<br>\uc5b4\ub5a4 \ub9c8\ubb3c\uc774\ub77c \ud574\ub3c4<br>\uc548 \ubb34\uc11c\uc6cc\ucfe0\ud3ec!", "Avec un pouvoir comme \u00e7a,<br>peu importe le monstre,<br>je n'ai plus peur de rien, kupo !", "Mit Kraft wie dieser<br>spielt das Monster keine Rolle mehr.<br>Ich f\u00fcrchte mich nicht, kupo!", "Con un poder como este,<br>no importa el monstruo que  sea.<br>\u00a1No me da miedo, kup\u00f3!"], "summon": ["Did you call me, kupo?<br>It's the Mog's turn to shine, kupo!", "\u2026\u2026\u5728\u53eb\u83ab\u53e4\u55ce\uff0c\u5eab\u5575\uff1f<br>\u7d42\u65bc\u8f2a\u5230\u83ab\u53e4\u5229\u4e0a\u5834\u4e86\uff0c\u5eab\u5575\uff01", "\u2026\u2026\ubd88\ub800\uc5b4\ucfe0\ud3ec?<br>\ub4dc\ub514\uc5b4 \ubaa8\uadf8 \ucc28\ub840\uac00 \uc628\uac70\uc57c\ucfe0\ud3ec~!", "Tu m'as appel\u00e9, kupo ?<br>C'est au tour des mogs de briller, kupo !", "Du hast mich gerufen, kupo?<br>Zeit f\u00fcr den Mogry, kupo!", "\u00bfMe llamaste, kup\u00f3?<br>\u00a1Es la hora de los moguri, kup\u00f3!"]}}, "100008805": {"growth_pattern": 30, "status_resist": [0, 0, 0, 0, 0, 0, 0, 0], "element_resist": [0, 0, 0, 0, 0, 0, 0, 0], "stats": {"HP": [724, 2193, 300], "ATK": [37, 111, 20], "MP": [39, 118, 50], "MAG": [27, 83, 20], "SPR": [30, 92, 20], "DEF": [27, 83, 20]}, "magic_affinity": [6, 0, 0, 0], "ability_slots": 4, "limitburst_id": 100008805, "attack_count": 100, "magical_resist": 0, "awakening": {"gil": 4000, "materials": {"290060300": 10, "290060000": 10, "290060100": 20, "290050500": 5, "290060400": 5}}, "rarity": 5, "compendium_id": 587, "attack_damage": [[100]], "max_lb_drop": 10, "physical_resist": 0, "attack_frames": [70], "effect_frames": [68], "strings": {"evolution": ["If you think us mogs are just cute,<br>then you've got another thing comin', kupo!", "\u4f60\u4ee5\u70ba\u83ab\u53e4\u53ea\u662f\u500b<br>\u53ef\u611b\u7684\u83ab\u53e4\u5229\u7684\u8a71\uff0c<br>\u5c31\u5927\u932f\u7279\u932f\u4e86\u5eab\u5575\uff01", "\ubaa8\uadf8\ub97c \uadf8\uc800 \uadc0\uc5ec\uc6b8 \ubfd0\uc778<br>\ubaa8\uadf8\ub9ac\ub85c \uc0dd\uac01\ud558\uba74<br>\ud070 \ucc29\uac01\ucfe0\ud3ec!", "Si tu penses que nous, les mogs, ne sommes que mignon,.<br>eh bien, tu risques d'\u00eatre surpris, kupo !", "Wenn du glaubst, dass Mogrys nur niedlich sind,<br>dann warte blo\u00df ab, kupo!", "Si crees que somos bonitos,<br>\u00a1pronto vas a dejar de pensar as\u00ed, kup\u00f3!"], "affinity": ["It's been a fun adventure with you, kupo!<br>I wish to give you this bubbly feeling as proof of our friendship, kupo.", "\u80fd\u8207\u4f60\u4e00\u8d77\u5192\u96aa\u771f\u662f\u592a\u9ad8\u8208\u4e86\uff0c\u5eab\u5575\uff01<br>\u7c21\u76f4\u60f3\u8981\u628a\u83ab\u53e4\u5229\u7684\u7d68\u7403<br>\u7576\u4f5c\u53cb\u60c5\u7684\u8b49\u660e\u9001\u7d66\u4f60\uff0c\u5eab\u5575\u3002", "\ub108\uc640 \ud568\uaed8 \ubaa8\ud5d8\ud560 \uc218 \uc788\uc5b4\uc11c \uae30\ubed0\ucfe0\ud3ec!<br>\uc6b0\uc815\uc758 \uc99d\uac70\ub85c, \ubaa8\uadf8\uc758 \ud3fc\ud3fc\uc744<br>\uc120\ubb3c\ud558\uace0 \uc2f6\uc744 \uc815\ub3c4\ucfe0\ud3ec.", "Nous avons v\u00e9cu une incroyable aventure ensemble, kupo !<br>J'aimerais te donner mon pompon comme gage de notre amiti\u00e9, kupo.", "Es macht Spa\u00df, Abenteuer mit dir zu erleben, kupo!<br>Nimm dieses Sprudeln als Zeichen unserer Freundschaft, kupo.", "\u00a1Ha sido una aventura muy divertida, kup\u00f3!<br>Como prueba de nuestra amistad, \u00a1te dejo este cosquilleo, kup\u00f3!"], "description": ["A moogle that serves King Mog in the Farplane, kupo! This moogle is such a go-getter that it was even entrusted with King Mog's personal guard. That's not to say that our king needs any help with monsters though. King Mog can easily destroy most of them in the blink of an eye, kupo! That's why this little moogle is so eager for a chance to prove its true abilities. Adventure awaits, kupo!", "\u5728\u7570\u754c\u7684\u57ce\u5821\u88e1\u4f8d\u5949\u83ab\u53e4\u5229\u738b\u7684\u83ab\u53e4\u5229\u5eab\u5575\uff01\u83ab\u53e4\u8eab\u624b\u4e86\u5f97\uff0c\u751a\u81f3\u7576\u904e\u570b\u738b\u7684\u8b77\u885b\u5eab\u5575\u3002\u4f46\u662f\u83ab\u53e4\u5011\u7684\u570b\u738b\u66f4\u52a0\u53b2\u5bb3\uff0c\u4e00\u822c\u7684\u9b54\u7269\u7260\u7728\u773c\u9593\u5c31\u80fd\u6253\u5012\u5eab\u5575\u3002\u83ab\u53e4\u9084\u6c92\u6709\u6a5f\u6703\u5c55\u73fe\u771f\u6b63\u7684\u5be6\u529b\uff0c\u56e0\u6b64\u597d\u671f\u5f85\u4eca\u5f8c\u7684\u5192\u96aa\u5eab\u5575\uff01", "\uc774\uacc4\uc758 \uc131\uc5d0\uc11c \ubaa8\uadf8\ub9ac \uc655\uc744 \ubaa8\uadf8\ub9ac\ucfe0\ud3ec! \ubaa8\uadf8\ub294 \uc784\uae08\ub2d8\uc744 \ud638\uc704\ud55c \uc801\ub3c4 \uc788\uc744 \uc815\ub3c4\ub85c, \uc2e4\ub825\uc774 \ub6f0\uc5b4\ub09c \ubaa8\uadf8\ub9ac\ucfe0\ud3ec. \ud558\uc9c0\ub9cc, \ubaa8\uadf8\ub9ac \uc784\uae08\ub2d8\uc740 \uc6ec\ub9cc\ud55c \ub9c8\ubb3c\uc740 \uac00\ubccd\uac8c \uc4f0\ub7ec\ub728\ub9b4 \uc815\ub3c4\ub85c \uac15\ud574\ucfe0\ud3ec. \uc9c0\uae08\uae4c\uc9c0 \uc9c4\uc9dc \uc2e4\ub825\uc744 \ubc1c\ud718\ud560 \uae30\ud68c\uac00 \uc5c6\uc5c8\uc5b4\uc11c, \ubaa8\ud5d8\uc774 \uae30\ub300\ub3fc\ucfe0\ud3ec!", "Un mog au service du roi Mog dans l'Au-del\u00e0, kupo\u00a0! La motivation et la volont\u00e9 de ce mog sont telles qu\u2019on lui a confi\u00e9 la garde personnelle du roi Mog. Ce qui ne revient pas \u00e0 dire que notre bon roi a besoin d\u2019aide pour se d\u00e9barrasser des monstres, oh que non. Le roi Mog peut ais\u00e9ment les an\u00e9antir en un clin d\u2019\u0153il, kupo\u00a0! Et c\u2019est pour cette raison que ce petit mog tr\u00e9pigne d\u2019impatience \u00e0 l\u2019id\u00e9e de mettre ses talents \u00e0 l\u2019\u00e9preuve. L\u2019aventure attend, kupo\u00a0!", "Ein Mogry, der dem Mogryk\u00f6nig im Schloss einer fernen Welt dient, kupo! Dieser Mogry ist so ein Draufg\u00e4nger, dass ihm von Majest\u00e4t Mogry sogar der Posten der Leibgarde anvertraut wurde, kupo. Unser K\u00f6nig ist allerdings so stark, dass er beinahe jedem Monster im Nu den Garaus macht, kupo. Deswegen hatte dieser Mogry bisher kaum Gelegenheit, sein K\u00f6nnen unter Beweis zu stellen - Waidmannsheil, kupo!", "\u00a1Un moguri que sirve al Rey moguri en el Et\u00e9reo, kup\u00f3! Este moguri es tan ambicioso que acab\u00f3 perteneciendo a la guardia personal del rey, lo cual no significa que nuestro rey necesite ayuda para luchar contra los monstruos. \u00a1El Rey moguri puede destruir a casi cualquier enemigo en un abrir y cerrar de ojos, kup\u00f3! Por eso, este peque\u00f1o moguri tiene tantas ganas de probar sus habilidades. \u00a1La aventura nos espera, kup\u00f3!"], "fusion": ["You still have yet to see the true power of us mogs, kupo!", "\u83ab\u53e4\u5229\u771f\u6b63\u7684\u5be6\u529b\uff0c<br>\u624d\u4e0d\u662f\u53ea\u6709\u9019\u6a23\u5462\uff0c\u5eab\u5575\uff01", "\ubaa8\uadf8\uc758 \uc9c4\uc9dc \uc2e4\ub825\uc740,<br>\uc774 \uc815\ub3c4\uac00 \uc544\ub0d0\ucfe0\ud3ec!", "Tu n'as pas encore vu ce dont nous, les mogs, sommes v\u00e9ritablement capables, kupo !", "Du hast die wahre Macht der Mogrys noch nicht gesehen, kupo!", "\u00a1Todav\u00eda no has visto el verdadero poder los moguris, kup\u00f3!"], "summon": ["Just guarding the castle that<br>whole time got kind of boring, kupo!<br>I'll show you what I can do, kupo!", "\u53ea\u64d4\u4efb\u57ce\u5821\u7684\u8b66\u5099<br>\u771f\u7684\u6709\u9ede\u7121\u804a\u5eab\u5575\uff01<br>\u83ab\u53e4\u8981\u5927\u5c55\u8eab\u624b\u4e86\u5eab\u5575\uff01", "\uc2e4\uc740 \uc131\uc758 \uacbd\ube44\ub9cc \uc11c\ub290\ub77c<br>\uc880 \uc9c0\ub8e8\ud588\uc5b4\ucfe0\ud3ec!<br>\ud65c\uc57d\ud558\uc790\ucfe0\ud3ec~!", "Monter la garde au ch\u00e2teau pendant tout ce temps \u00e0 finir par devenir d'un ennui mortel, kupo !<br>Je vais te montrer ce que je sais faire, kupo !", "Immer das Schloss zu bewachen,<br>wurde mit der Zeit \u00f6de, kupo!<br>Ich zeige euch, was ich kann, kupo!", "\u00a1Vigilar el castillo sin parar<br>es muy aburrido, kup\u00f3!<br>\u00a1Te ense\u00f1ar\u00e9 lo que s\u00e9, kup\u00f3!"]}}, "100008806": {"growth_pattern": 30, "status_resist": [0, 0, 0, 0, 0, 0, 0, 0], "element_resist": [0, 0, 0, 0, 0, 0, 0, 0], "stats": {"HP": [941, 2852, 450], "ATK": [48, 145, 30], "MP": [51, 154, 75], "MAG": [36, 108, 30], "SPR": [40, 120, 30], "DEF": [36, 108, 30]}, "magic_affinity": [7, 0, 0, 0], "ability_slots": 4, "limitburst_id": 100008806, "attack_count": 100, "magical_resist": 0, "awakening": null, "rarity": 6, "compendium_id": 588, "attack_damage": [[100]], "max_lb_drop": 12, "physical_resist": 0, "attack_frames": [70], "effect_frames": [68], "strings": {"evolution": ["ku, ku, ku, kupo!<br>I'll show you what I can do, kupo!", "\u5eab\u3001\u5eab\u3001\u5eab\u2026\u2026\u5eab\u5575\uff01<br>\u8b93\u4f60\u770b\u770b\u83ab\u53e4\u8a8d\u771f\u7684\u6a23\u5b50\u5eab\u5575\uff01", "\ucfe0, \ucfe0, \ucfe0\u2026\u2026 \ucfe0\ud3ec!<br>\uc9c4\uc815\ud55c \ubaa8\uadf8\uc758 \ud798\uc744 \ubcf4\uc5ec\uc8fc\ub9c8\ucfe0\ud3ec!", "Ku, ku, ku, kupo !<br>Je vais te montrer de quel bois je me chauffe, kupo !", "Ku, ku, ku, kupo!<br>Ich zeige dir, was ich kann, kupo!", "\u00a1Ku, ku, ku, kup\u00f3!<br>\u00a1Te ense\u00f1ar\u00e9 de lo que soy capaz, kup\u00f3!"], "affinity": ["It's been a fun adventure with you, kupo!<br>I wish to give you this bubbly feeling as proof of our friendship, kupo.", "\u80fd\u8207\u4f60\u4e00\u8d77\u5192\u96aa\u771f\u662f\u592a\u9ad8\u8208\u4e86\uff0c\u5eab\u5575\uff01<br>\u7c21\u76f4\u60f3\u8981\u628a\u83ab\u53e4\u5229\u7684\u7d68\u7403<br>\u7576\u4f5c\u53cb\u60c5\u7684\u8b49\u660e\u9001\u7d66\u4f60\uff0c\u5eab\u5575\u3002", "\ub108\uc640 \ud568\uaed8 \ubaa8\ud5d8\ud560 \uc218 \uc788\uc5b4\uc11c \uae30\ubed0\ucfe0\ud3ec!<br>\uc6b0\uc815\uc758 \uc99d\uac70\ub85c, \ubaa8\uadf8\uc758 \ud3fc\ud3fc\uc744<br>\uc120\ubb3c\ud558\uace0 \uc2f6\uc744 \uc815\ub3c4\ucfe0\ud3ec.", "Nous avons v\u00e9cu une incroyable aventure ensemble, kupo !<br>J'aimerais te donner mon pompon comme gage de notre amiti\u00e9, kupo.", "Es macht Spa\u00df, Abenteuer mit dir zu erleben, kupo!<br>Nimm dieses Sprudeln als Zeichen unserer Freundschaft, kupo.", "\u00a1Ha sido una aventura muy divertida, kup\u00f3!<br>Como prueba de nuestra amistad, \u00a1te dejo este cosquilleo, kup\u00f3!"], "description": ["A moogle that serves King Mog in the Farplane, kupo! There are many strong moogles who guard the king, but this particular moogle has proved itself above all others. You have to believe me, kupo! Moogle has been a fierce protector of the castle for quite some time now. If you ask me though, I think it would much rather find a place where it can really prove its worth, kupo!", "\u5728\u7570\u754c\u7684\u57ce\u5821\u88e1\u4f8d\u5949\u83ab\u53e4\u5229\u738b\u7684\u83ab\u53e4\u5229\u5eab\u5575\uff01\u5728\u57ce\u88e1\u9762\u96d6\u7136\u6709\u5f88\u591a\u53b2\u5bb3\u7684\u83ab\u53e4\u5229\uff0c\u4f46\u83ab\u53e4\u66f4\u52dd\u4e00\u7c4c\u5eab\u5575\u2026\u2026\u9019\u662f\u771f\u7684\u5eab\u5575\uff01\u5eab\u5575\u81f3\u4eca\u90fd\u975e\u5e38\u8a8d\u771f\u5730\u64d4\u4efb\u57ce\u88e1\u8b66\u5099\u4e00\u8077\u5eab\u5575\u3002\u4f46\u5176\u5be6\u662f\u5728\u8a8d\u771f\u5c0b\u627e\u53ef\u4ee5\u771f\u6b63\u767c\u63ee\u81ea\u5df1\u5be6\u529b\u7684\u5730\u65b9\u5eab\u5575\u2026\u2026\uff01", "\uc774\uacc4\uc758 \uc131\uc5d0\uc11c \ubaa8\uadf8\ub9ac \uc655\uc744 \ubaa8\uc2dc\ub294 \ubaa8\uadf8\ub9ac\ucfe0\ud3ec! \uc131\uc5d0\ub294 \uac15\ud55c \ubaa8\uadf8\ub9ac\ub4e4\uc774 \ubc14\uae00\ubc14\uae00\ud558\uc9c0\ub9cc, \ubaa8\uadf8\ub294 \uadf8 \uc911\uc5d0\uc11c\ub3c4 \ud2b9\ud788 \ud55c\uc218 \uc704\uc778 \ubaa8\uadf8\ub9ac\ucfe0\ud3ec. \u2026\u2026\uc9c4\uc9dc\uc57c\ucfe0\ud3ec! \ubaa8\uadf8\ub294 \uc9c0\uae08\uae4c\uc9c0 \ucd5c\uc120\uc744 \ub2e4\ud574 \uc131\uc758 \uacbd\ube44 \uc5c5\ubb34\ub97c \ub3c4\ub9e1\uc544\uc654\uc5b4\ucfe0\ud3ec. \ud558\uc9c0\ub9cc \uc2e4\uc740, \uc9c4\uc9dc \uc2e4\ub825\uc744 \ubc1c\ud718\ud560 \uc218 \uc788\uc744 \uacf3\uc744 \ucc3e\uace0 \uc788\uc5c8\ub294\uc9c0\ub3c4 \ubab0\ub77c\ucfe0\ud3ec\u2026\u2026!", "Un mog au service du roi Mog dans l'Au-del\u00e0, kupo\u00a0! Le roi est gard\u00e9 par plusieurs mogs puissants, mais celui-ci a prouv\u00e9 sa sup\u00e9riorit\u00e9. Vous devez me croire, kupo\u00a0! Ce mog prot\u00e8ge f\u00e9rocement le ch\u00e2teau depuis longtemps \u00e0 pr\u00e9sent. Si vous voulez mon avis, ceci dit, je pense qu\u2019il pr\u00e9f\u00e9rerait trouver un endroit o\u00f9 il peut vraiment prouver sa valeur, kupo\u00a0!", "Ein Mogry, der dem Mogryk\u00f6nig im Schloss einer fernen Welt dient, kupo! Im Schloss wimmelt es nur so vor starken Mogrys, aber dieser Mogry ist wohl an wahrem K\u00f6nnen un\u00fcbertroffen! \u2026 Wirklich jetzt, kupo! Im Schloss hat Mogry bisher hart als Wache gearbeitet, kupo. In Wirklichkeit sucht er jedoch nach einem Ort, an dem er sein tats\u00e4chliches Potential entfalten kann, kupo \u2026!", "\u00a1Un moguri que sirve al Rey moguri en el Et\u00e9reo, kup\u00f3! Hay muchos moguris bastante fuertes que protegen al rey, pero este en especial ha probado estar por encima del resto. \u00a1Tienes que creerme, kup\u00f3! Este moguri ya lleva protegiendo el castillo mucho tiempo. Aunque si me preguntas, \u00a1creo que preferir\u00eda otro lugar donde pueda probar su val\u00eda, kup\u00f3!"], "fusion": ["This mog may just have become a bit too powerful, kupo!", "\u83ab\u53e4\u5229\u597d\u50cf\u4e0d\u5c0f\u5fc3<br>\u8b8a\u5f97\u592a\u5f37\u4e86\u5eab\u5575\uff01", "\ubaa8\uadf8, \uc9c0\ub098\uce58\uac8c \uac15\ud574\uc9c4 \uac83 \uac19\uc544\ucfe0\ud3ec\u2026!", "Ce mog est devenu un petit peu trop puissant, kupo !", "Dieser Mogry k\u00f6nnte zu m\u00e4chtig geworden sein, kupo!", "\u00a1Este moguri puede que ahora sea demasiado poderoso, kup\u00f3!"], "summon": ["I'm a famous soldier back in our<br>castle in the Farplane, kupo!<br>I'll show you exactly why, kupo!", "\u5728\u7570\u754c\u7684\u57ce\u5821\u4e2d\uff0c<br>\u83ab\u53e4\u5229\u53ef\u662f\u6709\u540d\u7684\u58eb\u5175\u5462\u5eab\u5575\uff01<br>\u8b93\u4f60\u770b\u770b\u771f\u6b63\u7684\u5be6\u529b\u5eab\u5575\uff01", "\ubaa8\uadf8\ub294 \uc774\uacc4\uc758 \uc131\uc5d0\uc120<br>\uc720\uba85\ud55c \ubcd1\uc0ac\ucfe0\ud3ec!<br>\ub0b4 \uc2e4\ub825\uc744 \ubcf4\uc5ec\uc904\uac8c\ucfe0\ud3ec~!", "Je suis un soldat tr\u00e8s connu dans notre ch\u00e2teau de l'Au-del\u00e0, kupo !<br>Je vais te montrer pourquoi, kupo !", "In unserem Schloss im Abyssum<br>bin ich ein bekannter Soldat, kupo!<br>Ich zeige euch, warum, kupo!", "\u00a1En nuestro castillo del Et\u00e9reo,<br>soy un conocido soldado, kup\u00f3!<br>\u00a1Te ense\u00f1ar\u00e9 por qu\u00e9, kup\u00f3!"]}}}, "job": "Moogle", "sex": "Other", "game": "FFBE", "rarity_max": 6, "names": ["Moogle", "\u83ab\u53e4\u5229", "\ubaa8\uadf8\ub9ac", "Mog", "Mogry", "Moguri"], "equip": [10, 40, 60], "game_id": 11001, "rarity_min": 4, "tribe_id": 8, "id": "100008804", "job_id": 110}