{"TMR": ["EQUIP", 409006300], "name": "Lightning", "is_summonable": true, "skills": [{"level": 6, "type": "ABILITY", "id": 202020, "rarity": 5}, {"level": 18, "type": "ABILITY", "id": 202030, "rarity": 5}, {"level": 24, "type": "ABILITY", "id": 202050, "rarity": 5}, {"level": 38, "type": "MAGIC", "id": 20220, "rarity": 5}, {"level": 42, "type": "ABILITY", "id": 100090, "rarity": 5}, {"level": 46, "type": "ABILITY", "id": 202070, "rarity": 5}, {"level": 56, "type": "MAGIC", "id": 10070, "rarity": 5}, {"level": 74, "type": "ABILITY", "id": 100740, "rarity": 5}, {"level": 80, "type": "ABILITY", "id": 202120, "rarity": 5}, {"level": 1, "type": "ABILITY", "id": 202010, "rarity": 6}, {"level": 20, "type": "ABILITY", "id": 202040, "rarity": 6}, {"level": 26, "type": "ABILITY", "id": 202060, "rarity": 6}, {"level": 48, "type": "ABILITY", "id": 202080, "rarity": 6}, {"level": 48, "type": "ABILITY", "id": 202100, "rarity": 6}, {"level": 48, "type": "ABILITY", "id": 202090, "rarity": 6}, {"level": 65, "type": "ABILITY", "id": 100020, "rarity": 6}, {"level": 72, "type": "ABILITY", "id": 202110, "rarity": 6}, {"level": 100, "type": "ABILITY", "id": 101370, "rarity": 6}], "sex_id": 2, "entries": {"213000106": {"growth_pattern": 6, "status_resist": [0, 0, 0, 0, 0, 0, 0, 0], "element_resist": [0, 0, 0, 0, 0, 0, 0, 0], "stats": {"HP": [1193, 3615, 450], "ATK": [48, 145, 30], "MP": [52, 157, 75], "MAG": [41, 123, 30], "SPR": [40, 120, 30], "DEF": [42, 126, 30]}, "magic_affinity": [4, 7, 4, 0], "ability_slots": 4, "limitburst_id": 213000106, "attack_count": 5, "magical_resist": 0, "awakening": null, "rarity": 6, "compendium_id": 279, "max_lb_drop": 2, "physical_resist": 0, "attack_frames": [14, 42, 68, 91, 134], "effect_frames": [12, 40, 66, 89, 124, 128, 132], "strings": {"evolution": "Destroying the world isn't salvation.<br>I'll keep fighting until the end.<br>This power will give me the strength.", "affinity": "When it looks like there's no hope left, we look harder until we find some. Always have, always will.", "description": "A woman who appears in the tales of a world where the gods toy with humanity's fate. Lightning chose to fight against the gods' servants, the fal'Cie, to save her sister Serah. Unfortunately, this resulted in Lightning herself being cursed as a \"l'Cie.\" The l'Cie were believed to be the enemies of peace; thus Lightning and her fellow l'Cie came to be persecuted by various enemies. Although not always in agreement, the l'Cie formed strong bonds with one another, seeking to fulfill their Focus in defiance of the gods.", "fusion": "It's not a question of can or can't.<br>There are some things in life you just do.", "summon": "Fighting without hope is no way to live. It's just a way to die. Now, show me the hope you've found."}}, "213000105": {"growth_pattern": 4, "status_resist": [0, 0, 0, 0, 0, 0, 0, 0], "element_resist": [0, 0, 0, 0, 0, 0, 0, 0], "stats": {"HP": [918, 2781, 300], "ATK": [37, 112, 20], "MP": [40, 121, 50], "MAG": [31, 95, 20], "SPR": [31, 93, 20], "DEF": [32, 97, 20]}, "magic_affinity": [3, 6, 3, 0], "ability_slots": 4, "limitburst_id": 213000105, "attack_count": 5, "magical_resist": 0, "awakening": {"gil": 4000, "materials": {"290060200": 10, "290060300": 5, "290060000": 20, "290060100": 10, "290050500": 5}}, "rarity": 5, "compendium_id": 278, "max_lb_drop": 2, "physical_resist": 0, "attack_frames": [14, 42, 68, 91, 134], "effect_frames": [12, 40, 66, 89, 124, 128, 132], "strings": {"evolution": null, "affinity": "When it looks like there's no hope left, we look harder until we find some. Always have, always will.", "description": "A woman who appears in the tales of a world where the gods toy with humanity's fate. Lightning is a soldier from the floating continent of Cocoon, ruled by servants of the gods known as the fal'Cie. Her unsociable and serious demeanor often makes her seem indifferent to those around her, when in reality she hides a gentle soul that drives her to face peril boldly to protect those she loves. Lightning gave up her post as a soldier to save her sister Serah, who had become a prisoner of the fal'Cie, and boarded a train full of unjustly exiled citizens to defy the fate the gods had chosen for her.", "fusion": "I don't take orders from fal'Cie.<br>How I live is up to me.", "summon": "Keep your eyes in front.<br>I'll watch the rear."}}}, "job": "l'Cie", "sex": "Female", "game": "FFXIII", "rarity_max": 6, "names": ["Lightning", "\u96f7\u5149", "\ub77c\uc774\ud2b8\ub2dd", "Lightning", "Lightning", "Lightning"], "equip": [1, 2, 3, 4, 7, 10, 14, 30, 40, 41, 50, 51, 52, 60], "game_id": 10013, "rarity_min": 5, "tribe_id": 5, "id": "213000105", "job_id": 60}