{"TMR": ["MATERIA", 504216990], "name": "Yda", "is_summonable": false, "skills": [{"level": 4, "type": "ABILITY", "id": 207870, "rarity": 4}, {"level": 30, "type": "ABILITY", "id": 101200, "rarity": 4}, {"level": 58, "type": "ABILITY", "id": 216970, "rarity": 4}, {"level": 1, "type": "ABILITY", "id": 216980, "rarity": 5}, {"level": 34, "type": "ABILITY", "id": 216960, "rarity": 5}, {"level": 80, "type": "ABILITY", "id": 216920, "rarity": 5}, {"level": 1, "type": "ABILITY", "id": 216910, "rarity": 6}, {"level": 22, "type": "ABILITY", "id": 216950, "rarity": 6}, {"level": 68, "type": "ABILITY", "id": 216930, "rarity": 6}, {"level": 100, "type": "ABILITY", "id": 216940, "rarity": 6}], "sex_id": 2, "entries": {"214000404": {"growth_pattern": 6, "status_resist": [0, 0, 0, 0, 0, 0, 0, 0], "element_resist": [0, 0, 0, 0, 0, 0, 0, 0], "stats": {"HP": [465, 1409, 210], "ATK": [23, 69, 18], "MP": [23, 68, 35], "MAG": [19, 56, 14], "SPR": [18, 53, 14], "DEF": [17, 52, 14]}, "magic_affinity": [0, 0, 0, 0], "ability_slots": 3, "limitburst_id": 214000404, "attack_count": 4, "magical_resist": 0, "awakening": {"gil": 2500, "materials": {"290031000": 8, "290030600": 13, "290050300": 15, "290050400": 8, "290020100": 25}}, "rarity": 4, "compendium_id": 760, "max_lb_drop": 2, "physical_resist": 0, "attack_frames": [17, 26, 42, 58], "effect_frames": [15, 24, 40, 56], "strings": {"evolution": null, "affinity": "I wanna fight with you someday!<br>I guarantee I won't lose!", "description": "A Hyur girl appearing in tales from Eorzea, a region in the faraway world of Hydaelyn. A member of the Scions of the Seventh Dawn, she is in charge of surveying the forest capital Gridania. She is an accomplished martial artist, and the power of her punches is much higher than one might think from looking at her petite build. She has a mysterious air about her given the fact her eyes are covered by the visor she wears, however in reality she is very cheerful and sociable.", "fusion": "Alright! Let's get to it!<br>The more the merrier!", "summon": "I wonder what sort of enemy we'll face. I look forward to pummeling them!"}}, "214000405": {"growth_pattern": 6, "status_resist": [0, 0, 0, 0, 0, 0, 0, 0], "element_resist": [0, 0, 0, 0, 0, 0, 0, 0], "stats": {"HP": [664, 2013, 240], "ATK": [33, 99, 24], "MP": [32, 98, 40], "MAG": [27, 81, 16], "SPR": [25, 77, 16], "DEF": [25, 75, 16]}, "magic_affinity": [0, 0, 0, 0], "ability_slots": 4, "limitburst_id": 214000405, "attack_count": 4, "magical_resist": 0, "awakening": {"gil": 4000, "materials": {"290060200": 10, "290060000": 10, "290060100": 5, "290050500": 5, "290060400": 20}}, "rarity": 5, "compendium_id": 761, "max_lb_drop": 3, "physical_resist": 0, "attack_frames": [17, 26, 42, 58], "effect_frames": [15, 24, 40, 56], "strings": {"evolution": "Looks like a new adventure's about to start! I can't help but be excited!", "affinity": "I wanna fight with you someday!<br>I guarantee I won't lose!", "description": "A Hyur girl appearing in tales from Eorzea, a region in the faraway world of Hydaelyn. As a member of the Scions of the Seventh Dawn, she is charged with investigating various problems, starting with the trouble with the primals. She is bright and positive, and though she is often being watched out for by her colleagues Y'shtola and Papalymo, her personality is often a source of inspiration, with her often setting the tone for most situations.", "fusion": "There we are!<br>Time to really let one loose!", "summon": "Sorry for the wait!<br>Leave the rest to me!"}}, "214000406": {"growth_pattern": 6, "status_resist": [0, 0, 0, 0, 0, 0, 0, 0], "element_resist": [0, 0, 0, 0, 0, 0, 0, 0], "stats": {"HP": [949, 2876, 390], "ATK": [47, 142, 34], "MP": [46, 140, 65], "MAG": [38, 116, 26], "SPR": [36, 110, 26], "DEF": [36, 108, 26]}, "magic_affinity": [0, 0, 0, 0], "ability_slots": 4, "limitburst_id": 214000406, "attack_count": 4, "magical_resist": 0, "awakening": null, "rarity": 6, "compendium_id": 762, "max_lb_drop": 3, "physical_resist": 0, "attack_frames": [17, 26, 42, 58], "effect_frames": [15, 24, 40, 56], "strings": {"evolution": "We all have the same dream!<br>I must keep it alive!", "affinity": "I wanna fight with you someday!<br>I guarantee I won't lose!", "description": "A Hyur girl appearing in tales from Eorzea, a region in the faraway world of Hydaelyn. As a member of the Scions of the Seventh Dawn, she is mainly focused on solving Gridania's primal problem. As full of vigor as she may be, she is not good at difficult conversation, and instead of using her head, she prefers moving her body. Good friends with Moenbryda, an authority on aetheryte techniques, she was happy to be reunited with her when she visited the Rising Stones headquarters.", "fusion": "I-I'm not sleeping! I was just engrossed in thought, th-that's all!", "summon": "Your support is here!<br>Nothing to worry about, I can handle this!"}}}, "job": "Scion", "sex": "Female", "game": "FFXIV", "rarity_max": 6, "names": ["Yda", "\u4f0a\u9054", "\uc774\ub2e4", "Yda", "Yda", "Yda"], "equip": [16, 40, 50, 51, 60], "game_id": 10014, "rarity_min": 4, "tribe_id": 5, "id": "214000404", "job_id": 99}