{"attack_type": "None", "unit_restriction": null, "name": "Imperial Helm", "icon": "ability_77.png", "id": "204320", "move_type": 4, "attack_count": [0], "effects_raw": [[0, 3, 1, [0, 5, 0, 0, 10, 0, 0]]], "effects": ["Increase HP by 10% and DEF by 5%"], "rarity": 5, "compendium_id": 489, "mp_cost": 0, "attack_frames": [[]], "effect_frames": [[]], "active": false, "element_inflict": null, "type": "ABILITY", "strings": {"name": ["Imperial Helm", "\u7687\u570b\u8ecd\u982d\u76d4", "\uc81c\uad6d\uad70\uc758 \ud5ec\uba67", "Casque de l'Empire", "Imperialer Helm", "Casco imperial"], "desc_short": ["Boost HP by 10% and DEF by 5%", "\u63d0\u9ad810%HP\u30015%\u9632\u79a6", "HP 10%, \ubc29\uc5b4\ub825 5% \uc0c1\uc2b9", "Augmente les PV de 10% et la DEF de 5%", "Erh\u00f6ht LP um 10 % und ABW um 5 %", "Aumenta la VIT un 10% y la DEF un 5%"], "desc_long": ["Boosts HP by 10% and DEF by 5%.", "\u63d0\u9ad810%HP\u30015%\u9632\u79a6\u6578\u503c\u3002", "HP\uac00 10%, \ubc29\uc5b4\ub825\uc774 5% \uc0c1\uc2b9\ud569\ub2c8\ub2e4.", "Augmente les PV de 10% et la DEF de 5%.", "Erh\u00f6ht LP um 10 % und ABW um 5 %.", "Aumenta la VIT un 10% y la DEF un 5%"]}, "effect_type": "Default"}