{"element_inflict": null, "effects_raw": [[0, 3, 2, [0, 0, 0, 0, 0, 0, 100, 0]], [0, 3, 1, [20, 0, 0, 0, 0, 0, 0]]], "attack_frames": [[]], "id": "215710", "attack_type": "None", "requirements": null, "move_type": 4, "effect_frames": [[]], "type": "ABILITY", "attack_count": [0], "unit_restriction": null, "motion_type": 3, "attack_damage": [[]], "effects": ["Increase resistance to Disease by 100%", "Increase ATK by 20%"], "active": false, "unique": false, "icon": "ability_19.png", "name": "Hybrid Lady", "rarity": 6, "compendium_id": 1630, "mp_cost": 0, "effect_type": "Default", "strings": {"name": ["Hybrid Lady", "\u6df7\u8840\u5973\u58eb", "\ud558\uc774\ube0c\ub9ac\ub4dc \ub808\uc774\ub514", "Dame hybride", "Hybride Dame", "Dama h\u00edbrida"], "desc_short": ["Boost ATK by 20% and nullify disease", "\u63d0\u9ad820%\u653b\u64ca\u7684\u6578\u503c+\u751f\u75c5\u7121\u6548", "\uacf5\uaca9\ub825 20% \uc0c1\uc2b9+\uc9c8\ubcd1 \ubb34\ud6a8\ud654", "Augmente l'ATT de 20% et annule maladie", "Erh\u00f6ht ANG um 20% und annulliert Virus.", "Aumenta el ATQ un 20% y anula enfermedad"], "desc_long": ["Boosts ATK by 20% and nullifies disease.", "\u63d0\u9ad820%\u653b\u64ca\u7684\u6578\u503c\uff0c\u751f\u75c5\u7121\u6548", "\uacf5\uaca9\ub825\uc774 20% \uc0c1\uc2b9\ud558\uace0, \uc9c8\ubcd1\uc744 \ubb34\ud6a8\ud654\ud569\ub2c8\ub2e4.", "Augmente l'ATT de 20% et annule maladie.", "Erh\u00f6ht ANG um 20% und annulliert Stille.", "Aumenta el ATQ un 20% y anula enfermedad."]}}