{"element_inflict": null, "effects_raw": [[1, 1, 6, [0, 0, 90, 0, 0, 0, 0, 0, 1]]], "attack_frames": [[]], "id": "219110", "attack_type": "None", "move_type": 4, "effect_frames": [[]], "type": "ABILITY", "attack_count": [0], "unit_restriction": null, "motion_type": 2, "attack_damage": [[]], "effects": ["Inflict Sleep (90%) on one enemy"], "active": true, "unique": false, "icon": "limit_00000.png", "name": "Sleep Buster", "rarity": 1, "compendium_id": 1970, "mp_cost": 0, "effect_type": "Default", "strings": {"name": ["Sleep Buster", "\u7761\u7720\u885d\u64ca", "\uc2ac\ub9ac\ud50c \ubc84\uc2a4\ud130", "Attaque Sommeil +", "Schlafj\u00e4ger", "Ataque Morfeo+"], "desc_short": ["Chance of putting one enemy to sleep", "\u4e00\u5b9a\u6a5f\u7387\u5c0d1\u540d\u6575\u4eba\u65bd\u52a0\u7761\u7720\u6548\u679c", "\uc801 1\uba85\uc5d0\uac8c \uc218\uba74 \ubd80\uc5ec", "Permet d'endormir un ennemi", "Chance, einen Gegner einschlafen zu lassen.", "Posibilidad de dormir a un enemigo"], "desc_long": ["Chance of putting one enemy to sleep.", "\u5c0d1\u540d\u6575\u4eba\u65bd\u52a0\u7761\u7720\u6548\u679c\u3002", "\uc801 1\uba85\uc744 \uc218\uba74 \uc0c1\ud0dc\uc5d0 \ube60\ub728\ub9bd\ub2c8\ub2e4.", "Permet d'endormir un ennemi.", "Chance, einen Gegner einschlafen zu lassen.", "Posibilidad de dormir a un enemigo."]}}