{"attack_type": "None", "unit_restriction": null, "name": "\u30d7\u30ed\u30c6\u30af\u30c8\u30c0\u30a6\u30f3", "icon": "ability_39.png", "id": "220320", "move_type": 1, "attack_count": [1], "effects_raw": [[2, 1, 24, [0, -50, 0, 0, 4, 1]]], "effects": ["Reduce DEF by 50% for 4 turns to all enemies"], "rarity": 4, "compendium_id": 2095, "mp_cost": 48, "attack_frames": [[120]], "effect_frames": [[40, 40, 40]], "active": true, "element_inflict": null, "type": "ABILITY", "strings": {"name": [], "desc_short": null, "desc_long": null}, "effect_type": "Default"}