{"element_inflict": null, "effects_raw": [[2, 2, 3, [0, 45, 0, 45, 3, 1]], [2, 2, 8, [400, 1, 200, 3]]], "attack_frames": [[]], "id": "222140", "attack_type": "None", "move_type": 4, "effect_frames": [[10, 40, 40]], "type": "ABILITY", "attack_count": [0], "unit_restriction": null, "motion_type": 2, "attack_damage": [[]], "effects": ["Increase DEF and SPR by 45% for 3 turns to all allies", "Restore 200 (+4x, Heal) HP split over 3 turns to all allies"], "active": true, "unique": false, "icon": "ability_63.png", "name": "Exceptional Tactics", "rarity": 6, "compendium_id": 2275, "mp_cost": 57, "effect_type": "Default", "strings": {"name": ["Exceptional Tactics", "\u7f55\u898b\u7684\u6230\u7565", "\ub6f0\uc5b4\ub09c \uad70\ub7b5", "Plan brillant", "Au\u00dfergew\u00f6hnliche Taktiken", "Plan brillante"], "desc_short": ["Boost DEF and SPR for all allies and gradually restore HP", "\u63d0\u9ad8\u5168\u9ad4\u968a\u54e1\u9632\u79a6\u7cbe\u795e\u7684\u6578\u503c+\u6301\u7e8c\u6062\u5fa9HP", "\uc544\uad70 \uc804\uccb4\uc758 \ubc29\uc5b4\ub825\uacfc \uc815\uc2e0\ub825 \uc0c1\uc2b9+HP \uc11c\uc11c\ud788 \ud68c\ubcf5", "Augmente la DEF et la PSY de tous les alli\u00e9s et restaure progressivement les PV", "Erh\u00f6ht ABW und PSY f\u00fcr alle Verb. und regeneriert allm\u00e4hlich LP.", "Aumenta la DEF y el ESP de todos los aliados y recupera la VIT poco a poco"], "desc_long": null}}