{"element_inflict": null, "effects_raw": [[1, 2, 19, [33, 2, 1]], [1, 2, 89, [0, 0, 0, 100, 0, 0, 2, 1]], [0, 3, 100, [2, 505370, 1, 9999, 1, 2]]], "attack_frames": [[]], "id": "222120", "attack_type": "None", "move_type": 4, "effect_frames": [[40, 40]], "type": "ABILITY", "attack_count": [0], "unit_restriction": null, "motion_type": 2, "attack_damage": [[]], "effects": ["Reduce magic damage taken by 24.812030075188% for 2 turns", "Increase break resistance to SPR by 100% for 2 turns to one ally", "Gain access to following skills (1 use):\n\tAscension (505370)"], "active": true, "unique": false, "icon": "ability_43.png", "name": "Magick Barrier", "rarity": 5, "compendium_id": 2273, "mp_cost": 24, "effect_type": "Default", "strings": {"name": ["Magick Barrier", "\u9006\u9b54\u6cd5", "\ubc14\ub9e4\uc9c1", "Barri\u00e8re magique", "Extot", "Antimagos"], "desc_short": ["Reduce magic damage taken for two turns and boost SPR reduction resistance for one ally, and enable ascension to be used one time", "2\u56de\u5408\u5167\u6e1b\u8f15\u5c0d1\u540d\u968a\u54e1\u9b54\u6cd5\u50b7\u5bb3+\u63d0\u9ad8\u964d\u4f4e\u7cbe\u795e\u7684\u8010\u6027+\u81ea\u8eab\u53ef\u4ee5\u4f7f\u75281\u6b21\u300c\u6607\u5929\u4e4b\u8def\u300d", "2\ud134 \ub3d9\uc548 \uc544\uad70 1\uba85\uc774 \ubc1b\ub294 \ub9c8\ubc95\ud53c\ud574\ub7c9 \uac10\uc18c+\uc815\uc2e0\ub825 \uac10\uc18c \uc800\ud56d\ub825 \uc0c1\uc2b9+\uc0ac\uc6a9\uc790\uac00 '\ud5a5\uc0c1' 1\ud68c \uc0ac\uc6a9 \uac00\ub2a5", "R\u00e9duit les d\u00e9g\u00e2ts physiques subis pendant 2 tours, augmente la r\u00e9sistance \u00e0 la baisse de DEF d'un alli\u00e9 et active une fois Ascension pour le lanceur", "Reduziert zwei Runden lang erhaltenen mag. Schaden und erh\u00f6ht Res. gegen PSY-Verringerung eines Verb. + erm\u00f6glicht einm. Anwendung von \"Ascention\".", "Reduce el da\u00f1o m\u00e1gico que se recibe durante 2 turnos, aumenta la res. contra la reducci\u00f3n de ESP a un aliado y aprende Ascensi\u00f3n (un uso)"], "desc_long": null}}