{"element_inflict": null, "effects_raw": [[0, 3, 98, [2, 505670, -1, [222610, 222620, 505690], 2, 1, 1]], [0, 3, 101, [40, 1, 1]], [0, 3, 100, [2, 505690, 9999, 2, 1]]], "attack_frames": [[40]], "id": "222830", "attack_type": "None", "move_type": 4, "effect_frames": [[40]], "type": "ABILITY", "attack_count": [1], "unit_restriction": null, "motion_type": 2, "attack_damage": [[100]], "effects": ["Gain 2 uses of the following skills for one turn:\n\tCrescent Moon (222610)\n\tSky High (505690)\n\tSoul Mates (222620) [not usable with 2H weapon]", "Reduce damage taken by 40% to caster for one turn", "Gain access to following skills for one turn:\n\tSky High (505690)"], "active": true, "unique": false, "icon": "ability_8.png", "name": "Default", "rarity": 6, "compendium_id": 2342, "mp_cost": 0, "effect_type": "Default", "strings": {"name": ["Default", "\u9ed8\u793a\u9304", "\ub514\ud3f4\ud2b8", "Default", "Default", "Default"], "desc_short": ["Reduce damage taken for self for one turn and enable bravery and sky high for one turn", "1\u56de\u5408\u5167\u6e1b\u5c11\u5c0d\u81ea\u8eab\u7684\u50b7\u5bb3+1\u56de\u5408\u5167\u53ef\u4ee5\u4f7f\u7528\u300c\u52c7\u6c23\u300d\u300c\u9ad8\u7a7a\u300d", "\uc0ac\uc6a9\uc790\uac00 \ubc1b\ub294 \ud53c\ud574\ub7c9  1\ud134 \ub3d9\uc548 \uac10\uc18c+1\ud134 \ub3d9\uc548 '\ube0c\ub808\uc774\ube0c', '\uace0\uacf5 \ube44\uc0c1' \uc0ac\uc6a9 \uac00\ub2a5", "R\u00e9duit les d\u00e9g\u00e2ts subis par le lanceur pendant un tour et active Bravoure et Au sommet pendant un tour", "Verringert eine Runde lang selbst erhaltenen Schaden und erm\u00f6glicht eine Runde lang Brave und Himmelhoch.", "Reduce el da\u00f1o que recibe el usuario durante un turno y aprende Bravura y Por las nubes durante un turno"], "desc_long": null}}