{"element_inflict": null, "effects_raw": [[1, 6, 16, [200]]], "attack_frames": [[110]], "id": "300210", "attack_type": "None", "requirements": null, "move_type": 4, "effect_frames": [[40, 40]], "type": "ABILITY", "attack_count": [1], "unit_restriction": null, "motion_type": 2, "attack_damage": [[100]], "effects": ["Restore 200 HP to target"], "active": true, "unique": false, "icon": "item_1000.png", "name": "Potion", "rarity": 1, "compendium_id": 10020, "mp_cost": 0, "effect_type": "Default", "strings": {"name": ["Potion", "\u6cbb\u7642\u5291", "\ud3ec\uc158", "Potion", "Trank", "Poci\u00f3n"], "desc_short": ["Restore a small amount of HP to one ally", "\u5c11\u91cf\u6062\u5fa91\u540d\u968a\u54e1\u7684HP", "\uc544\uad70 1\uba85\uc758 HP \uc18c\ub7c9 \ud68c\ubcf5", "R\u00e9g\u00e9n\u00e8re l\u00e9g\u00e8rement les PV d'un alli\u00e9", "Heilt einige LP eines Verb\u00fcndeten", "Recupera algo la VIT a un aliado"], "desc_long": ["A tonic that restores an ally's health by a small amount. Derived from an ancient recipe referenced in the histories of the Kingdom of Pharm, it is created by blending a number of medicinal herbs. In recent years, improvements to the formula and the wider availability of high-quality ingredients even in less prosperous lands, it is readily available across the realm.", "\u80fd\u5920\u5c11\u91cf\u6062\u5fa9\u968a\u54e1HP\u7684\u85e5\u3002\u7531\u591a\u7a2e\u85e5\u8349\u8abf\u914d\u800c\u6210\u3002\u6709\u8a18\u8f09\u8868\u660e\uff0c\u5176\u8d77\u6e90\u975e\u5e38\u53e4\u8001\uff0c\u5c31\u9023\u53e4\u4ee3\u6cd5\u723e\u59c6\u738b\u570b\u7684\u53e4\u6587\u66f8\u4e2d\u90fd\u6709\u8a18\u9304\u3002\u73fe\u4eca\uff0c\u6b64\u85e5\u7684\u8abf\u914d\u65b9\u6cd5\u5f97\u5230\u4e86\u666e\u53ca\uff0c\u85e5\u8349\u7684\u54c1\u7a2e\u4e5f\u5f97\u5230\u4e86\u6539\u826f\uff0c\u5c31\u7b97\u4e0d\u662f\u5f88\u80a5\u6c83\u7684\u571f\u5730\u4e5f\u80fd\u7a2e\u690d\u51fa\u539f\u6750\u6599\uff0c\u6240\u4ee5\u53ef\u4ee5\u7a69\u5b9a\u5730\u4f9b\u7d66\u4e16\u754c\u5404\u5730\u3002", "\uc544\uad70\uc758 HP\ub97c \uc18c\ub7c9 \ud68c\ubcf5\ud558\ub294 \uc57d. \uac16\uc740 \uc57d\ucd08\ub97c \uc11e\uc5b4\uc11c \ub9cc\ub4e0\ub2e4. \uc774 \uc57d\ud488\uc758 \uc5ed\uc0ac\ub294 \uc624\ub798\ub418\uc5c8\uc73c\uba70, \ud314\ub984 \uc655\uad6d \uc2dc\ub300\uc758 \uace0\ubb38\uc11c\uc5d0\uc11c\ub3c4 \uc874\uc7ac\ub97c \ucc3e\uc544\ubcfc \uc218 \uc788\ub2e4. \uc9c0\uae08\uc740 \uc870\ud569 \ubc29\ubc95\uc774 \ub110\ub9ac \uc54c\ub824\uc9c0\uace0, \uc6d0\ub8cc\ub85c \uc4f0\ub294 \uc57d\ucd08\ub3c4 \ud488\uc885\uac1c\ub7c9\uc774 \uc9c4\ud589\ub418\uc5b4 \ucc99\ubc15\ud55c \ud1a0\uc591\uc5d0\uc11c\ub3c4 \uc798 \uc790\ub77c\uae30 \ub54c\ubb38\uc5d0 \uc138\uacc4 \uac01\uc9c0\uc5d0\uc11c \uc548\uc815\uc801\uc73c\ub85c \uacf5\uae09\ub418\uace0 \uc788\ub2e4.", "Un tonifiant qui r\u00e9g\u00e9n\u00e8re un peu la sant\u00e9 d'un alli\u00e9. D\u00e9riv\u00e9 d'une ancienne recette r\u00e9f\u00e9renc\u00e9e dans les grimoires du royaume de Pharm, il est n\u00e9 du m\u00e9lange de plusieurs herbes m\u00e9dicinales et est disponible en abondance dans tout le royaume en raison d'am\u00e9liorations apport\u00e9es \u00e0 la formule et de la grande disponibilit\u00e9 d'ingr\u00e9dients de haute qualit\u00e9 jusque dans les r\u00e9gions les moins prosp\u00e8resistencia", "Ein Tonikum, das leichte Verletzungen heilt. Es basiert auf einer Mixtur verschiedener Heilkr\u00e4uter und wird nach einem alten Rezept aus den Chroniken des K\u00f6nigreichs Pharm hergestellt. Dank einer vereinfachten Rezeptur, die auf \u00fcberall erh\u00e4ltliche Zutaten zur\u00fcckgreift, findet man dieses Mittel seit einigen Jahren selbst in den \u00e4rmsten Regionen des Reiches.", "Un t\u00f3nico que recupera una peque\u00f1a cantidad de la salud de un aliado. Basada en una antigua receta que aparece en las cr\u00f3nicas del Reino de Pharm, se elabora mezclando cierta cantidad de hierbas medicinales. En los \u00faltimos a\u00f1os, gracias a mejoras en la f\u00f3rmula y a una mayor disponibilidad de ingredientes incluso en las zonas menos pr\u00f3speras han provocado que se encuentre f\u00e1cilmente por todo el reino."]}}