{"element_inflict": null, "effects_raw": [[1, 1, 102, [100, 99999, 500]], [1, 1, 34, [20, 20, 20, 20, 20, 20, 0, 0, 1, 3]]], "attack_frames": [[42, 72, 102]], "id": "505310", "attack_type": "Physical", "move_type": 4, "effect_frames": [[40, 110, 110, 0]], "type": "ABILITY", "attack_count": [3], "unit_restriction": null, "motion_type": 2, "attack_damage": [[20, 20, 60]], "effects": ["Physical damage (5x, DEF) to one enemy", "Inflict 3 random status effects (Poison, Blind, Sleep, Silence, Paralyze and Confusion 20%) to one enemy"], "active": true, "unique": false, "icon": "ability_14.png", "name": "Ruin Unflinching", "rarity": 7, "compendium_id": 10430, "mp_cost": 38, "effect_type": "Default", "strings": {"name": ["Ruin Unflinching", "\u7121\u754f\u7684\u7d42\u7d50", "\ub450\ub824\uc6c0 \uc5c6\ub294 \uc885\ub9d0", "An\u00e9antissement", "Keine Angst vor dem Tod", "Destrucci\u00f3n total"], "desc_short": ["Damage and randomly poison, blind, put to sleep, silence, paralyze, or confuse one enemy, and add frost purge effect next turn", "\u653b\u64ca1\u540d\u6575\u4eba+\u96a8\u6a5f\u65bd\u52a0\u6bd2\u5931\u660e\u7761\u7720\u6c89\u9ed8\u9ebb\u75fa\u6df7\u4e82\u7684\u6548\u679c+\u4e0b\u4e00\u56de\u5408\u8ce6\u4e88\u300c\u767e\u9b3c\u00b7\u79cb\u971c\u7684\u7834\u90aa\u300d\u8ffd\u52a0\u6548\u679c", "\uc801 1\uba85\uc5d0\uac8c \ud53c\ud574+\ubb34\uc791\uc704\ub85c \ub3c5, \uc554\ud751, \uc218\uba74, \uce68\ubb35, \ub9c8\ube44, \ud63c\ub780 \ubd80\uc5ec+\ub2e4\uc74c \ud134\uc5d0 '\ubc31\uadc0\u00b7\ucd94\uc0c1\uc758 \ud30c\uc0ac'\uc5d0 \ucd94\uac00 \ud6a8\uacfc \ubd80\uc5ec", "D\u00e9g\u00e2ts, inflige al\u00e9atoirement poison, c\u00e9cit\u00e9, sommeil, silence, paralysie ou confusion \u00e0 un ennemi, et active l'effet Lames purgatrices au tour suivant", "F\u00fcgt einem Gegner Schaden zu und f\u00fcgt zuf. Gift, Blind, Schlaf, L\u00e4hmung oder Konfus zu + wirkt in folgender Runde <br>Eisklingentanz-Effekt.", "Da\u00f1a e inflige al azar ven, ceg, sue, sil, par o con a un enemigo, a\u00f1ade Sables de hielo al turno sig."], "desc_long": null}}