{"element_inflict": null, "effects_raw": [[1, 1, 1, [0, 0, 0, 0, 0, 0, 580, 0]], [0, 3, 100, [[2, 2], [505610, 505620], 9999, 2, 1, 0]]], "attack_frames": [[2, 12, 22, 32]], "id": "505630", "attack_type": "Physical", "requirements": null, "move_type": 1, "effect_frames": [[0, 10, 20, 30]], "type": "ABILITY", "attack_count": [4], "unit_restriction": null, "motion_type": 1, "attack_damage": [[25, 25, 25, 25]], "effects": ["Physical damage (5.8x, ATK) to one enemy", "Gain access to following skills for one turn:\n\tBison Horn (505620)\n\tWolf Fang (505610)"], "active": true, "unique": false, "icon": "ability_54.png", "name": "Falcon Claw", "rarity": 7, "compendium_id": 10462, "mp_cost": 40, "effect_type": "Default", "strings": {"name": ["Falcon Claw", "\u9df9\u722a", "\ub9e4\uc758 \ubc1c\ud1b1", "Serre de faucon", "Falkenkralle", "Garra de halc\u00f3n"], "desc_short": ["Damage one enemy and enable wolf fang and bison horn for one turn", "\u653b\u64ca1\u540d\u6575\u4eba+1\u56de\u5408\u5167\u53ef\u4f7f\u7528\u300c\u72fc\u7259\u300d\u300c\u91ce\u725b\u89d2\u300d", "\uc801 1\uba85\uc5d0\uac8c \ud53c\ud574+1\ud134 \ub3d9\uc548 '\ub291\ub300\uc758 \uc1a1\uacf3\ub2c8', '\ub4e4\uc18c\uc758 \ubfd4' \uc0ac\uc6a9 \uac00\ub2a5", "D\u00e9g\u00e2ts \u00e0 un ennemi et active Croc de loup et Corne de bison pendant un tour", "F\u00fcgt einem Gegner Schaden zu und erm\u00f6glicht eine Runde lang Wolfszahn und Bisonhorn.", "Da\u00f1a a un enemigo y aprende Colmillo lupino y Cuerno bisontino durante un turno"], "desc_long": null}}