{"element_inflict": null, "effects_raw": [[1, 1, 42, [0, 0, 2, 2, 220, 50]]], "attack_frames": [[]], "id": "506720", "attack_type": "Physical", "requirements": null, "move_type": 1, "effect_frames": [[]], "type": "ABILITY", "attack_count": [0], "unit_restriction": null, "motion_type": 1, "attack_damage": [[]], "effects": ["2 physical attacks (2.2x each, 4.4x total, ATK) to one enemy"], "active": true, "unique": false, "icon": "ability_10.png", "name": "Two Birds One Stone", "rarity": 6, "compendium_id": 10532, "mp_cost": 15, "effect_type": "Default", "strings": {"name": ["Two Birds One Stone", "\u4e00\u77f3\u4e8c\u9ce5", "\uc77c\uc11d\uc774\uc870", "Une pierre, deux coups", "Zwei Fliegen mit einer Klappe", "Dos p\u00e1jaros de un tiro"], "desc_short": ["Damage one enemy 2 times", "\u5c0d1\u540d\u6575\u4eba\u767c\u52d52\u6b21\u653b\u64ca", "\uc801 1\uba85\uc5d0\uac8c 2\ud68c \ud53c\ud574", "Inflige 2 fois des d\u00e9g\u00e2ts \u00e0 un ennemi", "F\u00fcgt einem Gegner zwei Mal Schaden zu.", "Da\u00f1a a un enemigo dos veces"], "desc_long": null}}