{"attack_type": "Magic", "unit_restriction": null, "name": "Blood Rend", "icon": "ability_23.png", "move_type": 4, "attack_count": [1], "effects_raw": [[1, 1, 15, [0, 0, 0, 0, 0, 500]]], "effects": ["Magic water damage (5x, MAG) to one enemy"], "rarity": 8, "compendium_id": 9317, "mp_cost": 40, "attack_frames": [[90]], "effect_frames": [[30, 30]], "active": true, "element_inflict": ["Water"], "type": "ABILITY", "strings": {"name": ["Blood Rend", "\u8840\u8272\u6495\u88c2", "\ud53c\uc758 \uc5f4\ud30c", "D\u00e9chirure sanglante", "Blutriss", "Hemorragia sangrienta"], "desc_short": ["Boosted water damage to one enemy", "\u5c0d1\u540d\u6575\u4eba\u767c\u52d5\u6c34\u5c6c\u6027\u653b\u64ca", "\uc801 1\uba85\uc5d0 \ubb3c\uc18d\uc131 \ud53c\ud574", "Augmente les d\u00e9g\u00e2ts d'eau sur un ennemi", "F\u00fcgt einem Gegner erh\u00f6hten Wasserschaden zu.", "Inflige da\u00f1o de agua a un enemigo"], "desc_long": ["Deals boosted water damage to one enemy.", "\u5c0d1\u540d\u6575\u4eba\u767c\u52d5\u6c34\u5c6c\u6027\u653b\u64ca\u3002", "\uc801 1\uba85\uc5d0\uac8c \ubb3c\uc18d\uc131 \ud53c\ud574\ub97c \uc90d\ub2c8\ub2e4.", "Augmente les d\u00e9g\u00e2ts d'eau sur un ennemi.", "F\u00fcgt einem Gegner erh\u00f6hten Wasserschaden zu.", "Inflige da\u00f1o de agua a un enemigo"]}, "effect_type": "Default"}